day_04/RLC/RLC_4_bit.v
module full_adder(
    input a,
    input b,
    input cin,
    output sum,
    output cout);

    assign sum  = a ^ b ^ cin;
    assign cout = (a & b) | (b & cin) | (a & cin);
endmodule
module ripple_carry_adder(
	input [3:0] A,
	input [3:0] B,
	input Cin,
	output [3:0] Sum,
	output Cout);
     wire c1,c2,c3;
     full_adder inst1(A[0], B[0], Cin, Sum[0],c1);
     full_adder inst2(A[1], B[1], c1, Sum[1],c2);
     full_adder inst3(A[2], B[2], c2, Sum[2],c3);
     full_adder inst4(A[3], B[3], c3, Sum[3],Cout);
 endmodule

day_04/RCA/RCA_4_bit_tb.v
module ripple_carry_adder_tb();
    reg [3:0] A;
    reg [3:0] B;
    reg Cin;
    wire [3:0] Sum;
    wire Cout;
    integer i, j;
    ripple_carry_adder inst(.A(A),.B(B),.Cin(Cin),.Sum(Sum),.Cout(Cout));

    initial begin
        $monitor("time=%0t|A=%b|B=%b|Cin=%b|Sum=%b|Cout=%b",$time,A,B,Cin,Sum,Cout);
	$dumpfile("RLC.vcd");
	$dumpvars;
     for(i=0;i<16;i++) begin
       for(j=0;j<16;j++) begin
         A=i;B=j;Cin=0;
         #5;
         end
    end
    end
endmodule

day_04/RCA/RCA.vcd
$date
	Mon Oct 13 22:17:30 2025
$end
$version
	Icarus Verilog
$end
$timescale
	1s
$end
$scope module ripple_carry_adder_tb $end
$var wire 4 ! Sum [3:0] $end
$var wire 1 " Cout $end
$var reg 4 # A [3:0] $end
$var reg 4 $ B [3:0] $end
$var reg 1 % Cin $end
$var integer 32 & i [31:0] $end
$var integer 32 ' j [31:0] $end
$scope module inst $end
$var wire 4 ( A [3:0] $end
$var wire 4 ) B [3:0] $end
$var wire 1 % Cin $end
$var wire 1 * c3 $end
$var wire 1 + c2 $end
$var wire 1 , c1 $end
$var wire 4 - Sum [3:0] $end
$var wire 1 " Cout $end
$scope module inst1 $end
$var wire 1 . a $end
$var wire 1 / b $end
$var wire 1 % cin $end
$var wire 1 , cout $end
$var wire 1 0 sum $end
$upscope $end
$scope module inst2 $end
$var wire 1 1 a $end
$var wire 1 2 b $end
$var wire 1 , cin $end
$var wire 1 + cout $end
$var wire 1 3 sum $end
$upscope $end
$scope module inst3 $end
$var wire 1 4 a $end
$var wire 1 5 b $end
$var wire 1 + cin $end
$var wire 1 * cout $end
$var wire 1 6 sum $end
$upscope $end
$scope module inst4 $end
$var wire 1 7 a $end
$var wire 1 8 b $end
$var wire 1 * cin $end
$var wire 1 " cout $end
$var wire 1 9 sum $end
$upscope $end
$upscope $end
$upscope $end
$enddefinitions $end
$comment Show the parameter values. $end
$dumpall
$end
#0
$dumpvars
09
08
07
06
05
04
03
02
01
00
0/
0.
b0 -
0,
0+
0*
b0 )
b0 (
b0 '
b0 &
0%
b0 $
b0 #
0"
b0 !
$end
#5
b1 !
b1 -
10
1/
b1 $
b1 )
b1 '
#10
00
b10 !
b10 -
13
0/
12
b10 $
b10 )
b10 '
#15
b11 !
b11 -
10
1/
b11 $
b11 )
b11 '
#20
00
03
b100 !
b100 -
16
0/
02
15
b100 $
b100 )
b100 '
#25
b101 !
b101 -
10
1/
b101 $
b101 )
b101 '
#30
00
b110 !
b110 -
13
0/
12
b110 $
b110 )
b110 '
#35
b111 !
b111 -
10
1/
b111 $
b111 )
b111 '
#40
00
03
06
b1000 !
b1000 -
19
0/
02
05
18
b1000 $
b1000 )
b1000 '
#45
b1001 !
b1001 -
10
1/
b1001 $
b1001 )
b1001 '
#50
00
b1010 !
b1010 -
13
0/
12
b1010 $
b1010 )
b1010 '
#55
b1011 !
b1011 -
10
1/
b1011 $
b1011 )
b1011 '
#60
00
03
b1100 !
b1100 -
16
0/
02
15
b1100 $
b1100 )
b1100 '
#65
b1101 !
b1101 -
10
1/
b1101 $
b1101 )
b1101 '
#70
00
b1110 !
b1110 -
13
0/
12
b1110 $
b1110 )
b1110 '
#75
b1111 !
b1111 -
10
1/
b1111 $
b1111 )
b1111 '
#80
03
06
b1 !
b1 -
09
0/
02
05
08
1.
b0 $
b0 )
b1 #
b1 (
b1 &
b0 '
#85
13
1,
b10 !
b10 -
00
1/
b1 $
b1 )
b1 '
#90
06
0,
0+
10
b11 !
b11 -
13
0/
12
b10 $
b10 )
b10 '
#95
16
1+
03
1,
b100 !
b100 -
00
1/
b11 $
b11 )
b11 '
#100
09
0,
0+
0*
10
03
b101 !
b101 -
16
0/
02
15
b100 $
b100 )
b100 '
#105
13
1,
b110 !
b110 -
00
1/
b101 $
b101 )
b101 '
#110
09
0*
16
0,
0+
10
b111 !
b111 -
13
0/
12
b110 $
b110 )
b110 '
#115
19
1*
06
1+
03
1,
b1000 !
b1000 -
00
1/
b111 $
b111 )
b111 '
#120
0,
0+
0*
0"
10
03
06
b1001 !
b1001 -
19
0/
02
05
18
b1000 $
b1000 )
b1000 '
#125
13
1,
b1010 !
b1010 -
00
1/
b1001 $
b1001 )
b1001 '
#130
06
0,
0+
10
b1011 !
b1011 -
13
0/
12
b1010 $
b1010 )
b1010 '
#135
16
1+
03
1,
b1100 !
b1100 -
00
1/
b1011 $
b1011 )
b1011 '
#140
0"
19
0,
0+
0*
10
03
b1101 !
b1101 -
16
0/
02
15
b1100 $
b1100 )
b1100 '
#145
13
1,
b1110 !
b1110 -
00
1/
b1101 $
b1101 )
b1101 '
#150
0"
19
0*
16
0,
0+
10
b1111 !
b1111 -
13
0/
12
b1110 $
b1110 )
b1110 '
#155
1"
09
1*
06
1+
03
1,
b0 !
b0 -
00
1/
b1111 $
b1111 )
b1111 '
#160
0+
13
0*
0"
0,
06
b10 !
b10 -
09
0/
02
05
08
0.
11
b0 $
b0 )
b10 #
b10 (
b10 &
b0 '
#165
b11 !
b11 -
10
1/
b1 $
b1 )
b1 '
#170
16
1+
00
b100 !
b100 -
03
0/
12
b10 $
b10 )
b10 '
#175
b101 !
b101 -
10
1/
b11 $
b11 )
b11 '
#180
09
0+
0*
00
13
b110 !
b110 -
16
0/
02
15
b100 $
b100 )
b100 '
#185
b111 !
b111 -
10
1/
b101 $
b101 )
b101 '
#190
19
1*
06
1+
00
b1000 !
b1000 -
03
0/
12
b110 $
b110 )
b110 '
#195
b1001 !
b1001 -
10
1/
b111 $
b111 )
b111 '
#200
0+
0*
0"
00
13
06
b1010 !
b1010 -
19
0/
02
05
18
b1000 $
b1000 )
b1000 '
#205
b1011 !
b1011 -
10
1/
b1001 $
b1001 )
b1001 '
#210
16
1+
00
b1100 !
b1100 -
03
0/
12
b1010 $
b1010 )
b1010 '
#215
b1101 !
b1101 -
10
1/
b1011 $
b1011 )
b1011 '
#220
0"
19
0+
0*
00
13
b1110 !
b1110 -
16
0/
02
15
b1100 $
b1100 )
b1100 '
#225
b1111 !
b1111 -
10
1/
b1101 $
b1101 )
b1101 '
#230
1"
09
1*
06
1+
00
b0 !
b0 -
03
0/
12
b1110 $
b1110 )
b1110 '
#235
b1 !
b1 -
10
1/
b1111 $
b1111 )
b1111 '
#240
0+
0*
0"
13
06
b11 !
b11 -
09
0/
02
05
08
1.
b0 $
b0 )
b11 #
b11 (
b11 &
b0 '
#245
16
1+
03
1,
b100 !
b100 -
00
1/
b1 $
b1 )
b1 '
#250
0,
10
b101 !
b101 -
03
0/
12
b10 $
b10 )
b10 '
#255
13
1,
b110 !
b110 -
00
1/
b11 $
b11 )
b11 '
#260
0+
09
0,
0*
10
13
b111 !
b111 -
16
0/
02
15
b100 $
b100 )
b100 '
#265
19
1*
06
1+
03
1,
b1000 !
b1000 -
00
1/
b101 $
b101 )
b101 '
#270
0,
10
b1001 !
b1001 -
03
0/
12
b110 $
b110 )
b110 '
#275
13
1,
b1010 !
b1010 -
00
1/
b111 $
b111 )
b111 '
#280
0+
0,
0*
0"
10
13
06
b1011 !
b1011 -
19
0/
02
05
18
b1000 $
b1000 )
b1000 '
#285
16
1+
03
1,
b1100 !
b1100 -
00
1/
b1001 $
b1001 )
b1001 '
#290
0,
10
b1101 !
b1101 -
03
0/
12
b1010 $
b1010 )
b1010 '
#295
13
1,
b1110 !
b1110 -
00
1/
b1011 $
b1011 )
b1011 '
#300
0"
0+
19
0,
0*
10
13
b1111 !
b1111 -
16
0/
02
15
b1100 $
b1100 )
b1100 '
#305
1"
09
1*
06
1+
03
1,
b0 !
b0 -
00
1/
b1101 $
b1101 )
b1101 '
#310
0,
10
b1 !
b1 -
03
0/
12
b1110 $
b1110 )
b1110 '
#315
13
1,
b10 !
b10 -
00
1/
b1111 $
b1111 )
b1111 '
#320
0*
03
16
0"
0,
0+
b100 !
b100 -
09
0/
02
05
08
0.
01
14
b0 $
b0 )
b100 #
b100 (
b100 &
b0 '
#325
b101 !
b101 -
10
1/
b1 $
b1 )
b1 '
#330
00
b110 !
b110 -
13
0/
12
b10 $
b10 )
b10 '
#335
b111 !
b111 -
10
1/
b11 $
b11 )
b11 '
#340
19
1*
00
03
b1000 !
b1000 -
06
0/
02
15
b100 $
b100 )
b100 '
#345
b1001 !
b1001 -
10
1/
b101 $
b101 )
b101 '
#350
00
b1010 !
b1010 -
13
0/
12
b110 $
b110 )
b110 '
#355
b1011 !
b1011 -
10
1/
b111 $
b111 )
b111 '
#360
0*
0"
00
03
16
b1100 !
b1100 -
19
0/
02
05
18
b1000 $
b1000 )
b1000 '
#365
b1101 !
b1101 -
10
1/
b1001 $
b1001 )
b1001 '
#370
00
b1110 !
b1110 -
13
0/
12
b1010 $
b1010 )
b1010 '
#375
b1111 !
b1111 -
10
1/
b1011 $
b1011 )
b1011 '
#380
1"
09
1*
00
03
b0 !
b0 -
06
0/
02
15
b1100 $
b1100 )
b1100 '
#385
b1 !
b1 -
10
1/
b1101 $
b1101 )
b1101 '
#390
00
b10 !
b10 -
13
0/
12
b1110 $
b1110 )
b1110 '
#395
b11 !
b11 -
10
1/
b1111 $
b1111 )
b1111 '
#400
0*
0"
03
16
b101 !
b101 -
09
0/
02
05
08
1.
b0 $
b0 )
b101 #
b101 (
b101 &
b0 '
#405
13
1,
b110 !
b110 -
00
1/
b1 $
b1 )
b1 '
#410
09
0*
16
0,
0+
10
b111 !
b111 -
13
0/
12
b10 $
b10 )
b10 '
#415
19
1*
06
1+
03
1,
b1000 !
b1000 -
00
1/
b11 $
b11 )
b11 '
#420
0,
0+
10
03
b1001 !
b1001 -
06
0/
02
15
b100 $
b100 )
b100 '
#425
13
1,
b1010 !
b1010 -
00
1/
b101 $
b101 )
b101 '
#430
06
0,
0+
10
b1011 !
b1011 -
13
0/
12
b110 $
b110 )
b110 '
#435
16
1+
03
1,
b1100 !
b1100 -
00
1/
b111 $
b111 )
b111 '
#440
0*
0,
0+
0"
10
03
16
b1101 !
b1101 -
19
0/
02
05
18
b1000 $
b1000 )
b1000 '
#445
13
1,
b1110 !
b1110 -
00
1/
b1001 $
b1001 )
b1001 '
#450
0"
19
0*
16
0,
0+
10
b1111 !
b1111 -
13
0/
12
b1010 $
b1010 )
b1010 '
#455
1"
09
1*
06
1+
03
1,
b0 !
b0 -
00
1/
b1011 $
b1011 )
b1011 '
#460
0,
0+
10
03
b1 !
b1 -
06
0/
02
15
b1100 $
b1100 )
b1100 '
#465
13
1,
b10 !
b10 -
00
1/
b1101 $
b1101 )
b1101 '
#470
06
0,
0+
10
b11 !
b11 -
13
0/
12
b1110 $
b1110 )
b1110 '
#475
16
1+
03
1,
b100 !
b100 -
00
1/
b1111 $
b1111 )
b1111 '
#480
0*
0+
13
0"
0,
16
b110 !
b110 -
09
0/
02
05
08
0.
11
b0 $
b0 )
b110 #
b110 (
b110 &
b0 '
#485
b111 !
b111 -
10
1/
b1 $
b1 )
b1 '
#490
19
1*
06
1+
00
b1000 !
b1000 -
03
0/
12
b10 $
b10 )
b10 '
#495
b1001 !
b1001 -
10
1/
b11 $
b11 )
b11 '
#500
0+
00
13
b1010 !
b1010 -
06
0/
02
15
b100 $
b100 )
b100 '
#505
b1011 !
b1011 -
10
1/
b101 $
b101 )
b101 '
#510
16
1+
00
b1100 !
b1100 -
03
0/
12
b110 $
b110 )
b110 '
#515
b1101 !
b1101 -
10
1/
b111 $
b111 )
b111 '
#520
0*
0+
0"
00
13
16
b1110 !
b1110 -
19
0/
02
05
18
b1000 $
b1000 )
b1000 '
#525
b1111 !
b1111 -
10
1/
b1001 $
b1001 )
b1001 '
#530
1"
09
1*
06
1+
00
b0 !
b0 -
03
0/
12
b1010 $
b1010 )
b1010 '
#535
b1 !
b1 -
10
1/
b1011 $
b1011 )
b1011 '
#540
0+
00
13
b10 !
b10 -
06
0/
02
15
b1100 $
b1100 )
b1100 '
#545
b11 !
b11 -
10
1/
b1101 $
b1101 )
b1101 '
#550
16
1+
00
b100 !
b100 -
03
0/
12
b1110 $
b1110 )
b1110 '
#555
b101 !
b101 -
10
1/
b1111 $
b1111 )
b1111 '
#560
0*
0+
0"
13
16
b111 !
b111 -
09
0/
02
05
08
1.
b0 $
b0 )
b111 #
b111 (
b111 &
b0 '
#565
19
1*
06
1+
03
1,
b1000 !
b1000 -
00
1/
b1 $
b1 )
b1 '
#570
0,
10
b1001 !
b1001 -
03
0/
12
b10 $
b10 )
b10 '
#575
13
1,
b1010 !
b1010 -
00
1/
b11 $
b11 )
b11 '
#580
0+
0,
10
13
b1011 !
b1011 -
06
0/
02
15
b100 $
b100 )
b100 '
#585
16
1+
03
1,
b1100 !
b1100 -
00
1/
b101 $
b101 )
b101 '
#590
0,
10
b1101 !
b1101 -
03
0/
12
b110 $
b110 )
b110 '
#595
13
1,
b1110 !
b1110 -
00
1/
b111 $
b111 )
b111 '
#600
0*
0+
0,
0"
10
13
16
b1111 !
b1111 -
19
0/
02
05
18
b1000 $
b1000 )
b1000 '
#605
1"
09
1*
06
1+
03
1,
b0 !
b0 -
00
1/
b1001 $
b1001 )
b1001 '
#610
0,
10
b1 !
b1 -
03
0/
12
b1010 $
b1010 )
b1010 '
#615
13
1,
b10 !
b10 -
00
1/
b1011 $
b1011 )
b1011 '
#620
0+
0,
10
13
b11 !
b11 -
06
0/
02
15
b1100 $
b1100 )
b1100 '
#625
16
1+
03
1,
b100 !
b100 -
00
1/
b1101 $
b1101 )
b1101 '
#630
0,
10
b101 !
b101 -
03
0/
12
b1110 $
b1110 )
b1110 '
#635
13
1,
b110 !
b110 -
00
1/
b1111 $
b1111 )
b1111 '
#640
0"
03
06
b1000 !
b1000 -
19
0,
0+
0*
0/
02
05
08
0.
01
04
17
b0 $
b0 )
b1000 #
b1000 (
b1000 &
b0 '
#645
b1001 !
b1001 -
10
1/
b1 $
b1 )
b1 '
#650
00
b1010 !
b1010 -
13
0/
12
b10 $
b10 )
b10 '
#655
b1011 !
b1011 -
10
1/
b11 $
b11 )
b11 '
#660
00
03
b1100 !
b1100 -
16
0/
02
15
b100 $
b100 )
b100 '
#665
b1101 !
b1101 -
10
1/
b101 $
b101 )
b101 '
#670
00
b1110 !
b1110 -
13
0/
12
b110 $
b110 )
b110 '
#675
b1111 !
b1111 -
10
1/
b111 $
b111 )
b111 '
#680
1"
00
03
06
b0 !
b0 -
09
0/
02
05
18
b1000 $
b1000 )
b1000 '
#685
b1 !
b1 -
10
1/
b1001 $
b1001 )
b1001 '
#690
00
b10 !
b10 -
13
0/
12
b1010 $
b1010 )
b1010 '
#695
b11 !
b11 -
10
1/
b1011 $
b1011 )
b1011 '
#700
00
03
b100 !
b100 -
16
0/
02
15
b1100 $
b1100 )
b1100 '
#705
b101 !
b101 -
10
1/
b1101 $
b1101 )
b1101 '
#710
00
b110 !
b110 -
13
0/
12
b1110 $
b1110 )
b1110 '
#715
b111 !
b111 -
10
1/
b1111 $
b1111 )
b1111 '
#720
0"
03
06
b1001 !
b1001 -
19
0/
02
05
08
1.
b0 $
b0 )
b1001 #
b1001 (
b1001 &
b0 '
#725
13
1,
b1010 !
b1010 -
00
1/
b1 $
b1 )
b1 '
#730
06
0,
0+
10
b1011 !
b1011 -
13
0/
12
b10 $
b10 )
b10 '
#735
16
1+
03
1,
b1100 !
b1100 -
00
1/
b11 $
b11 )
b11 '
#740
0"
19
0,
0+
0*
10
03
b1101 !
b1101 -
16
0/
02
15
b100 $
b100 )
b100 '
#745
13
1,
b1110 !
b1110 -
00
1/
b101 $
b101 )
b101 '
#750
0"
19
0*
16
0,
0+
10
b1111 !
b1111 -
13
0/
12
b110 $
b110 )
b110 '
#755
1"
09
1*
06
1+
03
1,
b0 !
b0 -
00
1/
b111 $
b111 )
b111 '
#760
0,
0+
0*
10
03
06
b1 !
b1 -
09
0/
02
05
18
b1000 $
b1000 )
b1000 '
#765
13
1,
b10 !
b10 -
00
1/
b1001 $
b1001 )
b1001 '
#770
06
0,
0+
10
b11 !
b11 -
13
0/
12
b1010 $
b1010 )
b1010 '
#775
16
1+
03
1,
b100 !
b100 -
00
1/
b1011 $
b1011 )
b1011 '
#780
09
0,
0+
0*
10
03
b101 !
b101 -
16
0/
02
15
b1100 $
b1100 )
b1100 '
#785
13
1,
b110 !
b110 -
00
1/
b1101 $
b1101 )
b1101 '
#790
09
0*
16
0,
0+
10
b111 !
b111 -
13
0/
12
b1110 $
b1110 )
b1110 '
#795
19
1*
06
1+
03
1,
b1000 !
b1000 -
00
1/
b1111 $
b1111 )
b1111 '
#800
0"
0+
13
0*
0,
06
b1010 !
b1010 -
19
0/
02
05
08
0.
11
b0 $
b0 )
b1010 #
b1010 (
b1010 &
b0 '
#805
b1011 !
b1011 -
10
1/
b1 $
b1 )
b1 '
#810
16
1+
00
b1100 !
b1100 -
03
0/
12
b10 $
b10 )
b10 '
#815
b1101 !
b1101 -
10
1/
b11 $
b11 )
b11 '
#820
0"
19
0+
0*
00
13
b1110 !
b1110 -
16
0/
02
15
b100 $
b100 )
b100 '
#825
b1111 !
b1111 -
10
1/
b101 $
b101 )
b101 '
#830
1"
09
1*
06
1+
00
b0 !
b0 -
03
0/
12
b110 $
b110 )
b110 '
#835
b1 !
b1 -
10
1/
b111 $
b111 )
b111 '
#840
0+
0*
00
13
06
b10 !
b10 -
09
0/
02
05
18
b1000 $
b1000 )
b1000 '
#845
b11 !
b11 -
10
1/
b1001 $
b1001 )
b1001 '
#850
16
1+
00
b100 !
b100 -
03
0/
12
b1010 $
b1010 )
b1010 '
#855
b101 !
b101 -
10
1/
b1011 $
b1011 )
b1011 '
#860
09
0+
0*
00
13
b110 !
b110 -
16
0/
02
15
b1100 $
b1100 )
b1100 '
#865
b111 !
b111 -
10
1/
b1101 $
b1101 )
b1101 '
#870
19
1*
06
1+
00
b1000 !
b1000 -
03
0/
12
b1110 $
b1110 )
b1110 '
#875
b1001 !
b1001 -
10
1/
b1111 $
b1111 )
b1111 '
#880
0"
0+
0*
13
06
b1011 !
b1011 -
19
0/
02
05
08
1.
b0 $
b0 )
b1011 #
b1011 (
b1011 &
b0 '
#885
16
1+
03
1,
b1100 !
b1100 -
00
1/
b1 $
b1 )
b1 '
#890
0,
10
b1101 !
b1101 -
03
0/
12
b10 $
b10 )
b10 '
#895
13
1,
b1110 !
b1110 -
00
1/
b11 $
b11 )
b11 '
#900
0+
0"
19
0,
0*
10
13
b1111 !
b1111 -
16
0/
02
15
b100 $
b100 )
b100 '
#905
1"
09
1*
06
1+
03
1,
b0 !
b0 -
00
1/
b101 $
b101 )
b101 '
#910
0,
10
b1 !
b1 -
03
0/
12
b110 $
b110 )
b110 '
#915
13
1,
b10 !
b10 -
00
1/
b111 $
b111 )
b111 '
#920
0+
0,
0*
10
13
06
b11 !
b11 -
09
0/
02
05
18
b1000 $
b1000 )
b1000 '
#925
16
1+
03
1,
b100 !
b100 -
00
1/
b1001 $
b1001 )
b1001 '
#930
0,
10
b101 !
b101 -
03
0/
12
b1010 $
b1010 )
b1010 '
#935
13
1,
b110 !
b110 -
00
1/
b1011 $
b1011 )
b1011 '
#940
0+
09
0,
0*
10
13
b111 !
b111 -
16
0/
02
15
b1100 $
b1100 )
b1100 '
#945
19
1*
06
1+
03
1,
b1000 !
b1000 -
00
1/
b1101 $
b1101 )
b1101 '
#950
0,
10
b1001 !
b1001 -
03
0/
12
b1110 $
b1110 )
b1110 '
#955
13
1,
b1010 !
b1010 -
00
1/
b1111 $
b1111 )
b1111 '
#960
0"
0*
03
16
0,
0+
b1100 !
b1100 -
19
0/
02
05
08
0.
01
14
b0 $
b0 )
b1100 #
b1100 (
b1100 &
b0 '
#965
b1101 !
b1101 -
10
1/
b1 $
b1 )
b1 '
#970
00
b1110 !
b1110 -
13
0/
12
b10 $
b10 )
b10 '
#975
b1111 !
b1111 -
10
1/
b11 $
b11 )
b11 '
#980
1"
09
1*
00
03
b0 !
b0 -
06
0/
02
15
b100 $
b100 )
b100 '
#985
b1 !
b1 -
10
1/
b101 $
b101 )
b101 '
#990
00
b10 !
b10 -
13
0/
12
b110 $
b110 )
b110 '
#995
b11 !
b11 -
10
1/
b111 $
b111 )
b111 '
#1000
0*
00
03
16
b100 !
b100 -
09
0/
02
05
18
b1000 $
b1000 )
b1000 '
#1005
b101 !
b101 -
10
1/
b1001 $
b1001 )
b1001 '
#1010
00
b110 !
b110 -
13
0/
12
b1010 $
b1010 )
b1010 '
#1015
b111 !
b111 -
10
1/
b1011 $
b1011 )
b1011 '
#1020
19
1*
00
03
b1000 !
b1000 -
06
0/
02
15
b1100 $
b1100 )
b1100 '
#1025
b1001 !
b1001 -
10
1/
b1101 $
b1101 )
b1101 '
#1030
00
b1010 !
b1010 -
13
0/
12
b1110 $
b1110 )
b1110 '
#1035
b1011 !
b1011 -
10
1/
b1111 $
b1111 )
b1111 '
#1040
0"
0*
03
16
b1101 !
b1101 -
19
0/
02
05
08
1.
b0 $
b0 )
b1101 #
b1101 (
b1101 &
b0 '
#1045
13
1,
b1110 !
b1110 -
00
1/
b1 $
b1 )
b1 '
#1050
0"
19
0*
16
0,
0+
10
b1111 !
b1111 -
13
0/
12
b10 $
b10 )
b10 '
#1055
1"
09
1*
06
1+
03
1,
b0 !
b0 -
00
1/
b11 $
b11 )
b11 '
#1060
0,
0+
10
03
b1 !
b1 -
06
0/
02
15
b100 $
b100 )
b100 '
#1065
13
1,
b10 !
b10 -
00
1/
b101 $
b101 )
b101 '
#1070
06
0,
0+
10
b11 !
b11 -
13
0/
12
b110 $
b110 )
b110 '
#1075
16
1+
03
1,
b100 !
b100 -
00
1/
b111 $
b111 )
b111 '
#1080
0*
0,
0+
10
03
16
b101 !
b101 -
09
0/
02
05
18
b1000 $
b1000 )
b1000 '
#1085
13
1,
b110 !
b110 -
00
1/
b1001 $
b1001 )
b1001 '
#1090
09
0*
16
0,
0+
10
b111 !
b111 -
13
0/
12
b1010 $
b1010 )
b1010 '
#1095
19
1*
06
1+
03
1,
b1000 !
b1000 -
00
1/
b1011 $
b1011 )
b1011 '
#1100
0,
0+
10
03
b1001 !
b1001 -
06
0/
02
15
b1100 $
b1100 )
b1100 '
#1105
13
1,
b1010 !
b1010 -
00
1/
b1101 $
b1101 )
b1101 '
#1110
06
0,
0+
10
b1011 !
b1011 -
13
0/
12
b1110 $
b1110 )
b1110 '
#1115
16
1+
03
1,
b1100 !
b1100 -
00
1/
b1111 $
b1111 )
b1111 '
#1120
0"
0*
0+
13
0,
16
b1110 !
b1110 -
19
0/
02
05
08
0.
11
b0 $
b0 )
b1110 #
b1110 (
b1110 &
b0 '
#1125
b1111 !
b1111 -
10
1/
b1 $
b1 )
b1 '
#1130
1"
09
1*
06
1+
00
b0 !
b0 -
03
0/
12
b10 $
b10 )
b10 '
#1135
b1 !
b1 -
10
1/
b11 $
b11 )
b11 '
#1140
0+
00
13
b10 !
b10 -
06
0/
02
15
b100 $
b100 )
b100 '
#1145
b11 !
b11 -
10
1/
b101 $
b101 )
b101 '
#1150
16
1+
00
b100 !
b100 -
03
0/
12
b110 $
b110 )
b110 '
#1155
b101 !
b101 -
10
1/
b111 $
b111 )
b111 '
#1160
0*
0+
00
13
16
b110 !
b110 -
09
0/
02
05
18
b1000 $
b1000 )
b1000 '
#1165
b111 !
b111 -
10
1/
b1001 $
b1001 )
b1001 '
#1170
19
1*
06
1+
00
b1000 !
b1000 -
03
0/
12
b1010 $
b1010 )
b1010 '
#1175
b1001 !
b1001 -
10
1/
b1011 $
b1011 )
b1011 '
#1180
0+
00
13
b1010 !
b1010 -
06
0/
02
15
b1100 $
b1100 )
b1100 '
#1185
b1011 !
b1011 -
10
1/
b1101 $
b1101 )
b1101 '
#1190
16
1+
00
b1100 !
b1100 -
03
0/
12
b1110 $
b1110 )
b1110 '
#1195
b1101 !
b1101 -
10
1/
b1111 $
b1111 )
b1111 '
#1200
0"
0*
0+
13
16
b1111 !
b1111 -
19
0/
02
05
08
1.
b0 $
b0 )
b1111 #
b1111 (
b1111 &
b0 '
#1205
1"
09
1*
06
1+
03
1,
b0 !
b0 -
00
1/
b1 $
b1 )
b1 '
#1210
0,
10
b1 !
b1 -
03
0/
12
b10 $
b10 )
b10 '
#1215
13
1,
b10 !
b10 -
00
1/
b11 $
b11 )
b11 '
#1220
0+
0,
10
13
b11 !
b11 -
06
0/
02
15
b100 $
b100 )
b100 '
#1225
16
1+
03
1,
b100 !
b100 -
00
1/
b101 $
b101 )
b101 '
#1230
0,
10
b101 !
b101 -
03
0/
12
b110 $
b110 )
b110 '
#1235
13
1,
b110 !
b110 -
00
1/
b111 $
b111 )
b111 '
#1240
0*
0+
0,
10
13
16
b111 !
b111 -
09
0/
02
05
18
b1000 $
b1000 )
b1000 '
#1245
19
1*
06
1+
03
1,
b1000 !
b1000 -
00
1/
b1001 $
b1001 )
b1001 '
#1250
0,
10
b1001 !
b1001 -
03
0/
12
b1010 $
b1010 )
b1010 '
#1255
13
1,
b1010 !
b1010 -
00
1/
b1011 $
b1011 )
b1011 '
#1260
0+
0,
10
13
b1011 !
b1011 -
06
0/
02
15
b1100 $
b1100 )
b1100 '
#1265
16
1+
03
1,
b1100 !
b1100 -
00
1/
b1101 $
b1101 )
b1101 '
#1270
0,
10
b1101 !
b1101 -
03
0/
12
b1110 $
b1110 )
b1110 '
#1275
13
1,
b1110 !
b1110 -
00
1/
b1111 $
b1111 )
b1111 '
#1280
b10000 &
b10000 '
