day_03/decoder/decoder3x8/decoder3x8.v
module decoder3x8 (
     	input [2:0]a,
	output [7:0]y);
	assign y[7] = ( ~a[2] & ~a[1] & ~a[0]);
        assign y[6] = ( ~a[2] & ~a[1] &  a[0]);  
	assign y[5] = ( ~a[2] &  a[1] & ~a[0]);  
	assign y[4] = ( ~a[2] &  a[1] &  a[0]);  
	assign y[3] = (  a[2] & ~a[1] & ~a[0]);  
	assign y[2] = (  a[2] & ~a[1] &  a[0]);  
	assign y[1] = (  a[2] &  a[1] & ~a[0]);  
	assign y[0] = (  a[2] &  a[1] &  a[0]);
endmodule

day_03/decoder/decoder3x8/decoder3x8_tb.v
module decoder3x8_tb();
	reg [2:0] a;
 	wire [7:0] y;
	integer i;
 decoder3x8 inst(a,y);
	initial begin
	$monitor("time=%0t| a=%b| y=%b",$time,a,y);
	$dumpfile("decoder3x8.vcd");
	$dumpvars;
	a='b000;
	for(i=0; i<8; i++)begin
        a=i;
	#5;
        end

        $finish;
	end
endmodule

day_03/decoder/decoder3x8/decoder3x8.vcd
$date
	Sun Oct 12 18:10:46 2025
$end
$version
	Icarus Verilog
$end
$timescale
	1s
$end
$scope module decoder3x8_tb $end
$var wire 8 ! y [7:0] $end
$var reg 3 " a [2:0] $end
$var integer 32 # i [31:0] $end
$scope module inst $end
$var wire 3 $ a [2:0] $end
$var wire 8 % y [7:0] $end
$upscope $end
$upscope $end
$enddefinitions $end
$comment Show the parameter values. $end
$dumpall
$end
#0
$dumpvars
b10000000 %
b0 $
b0 #
b0 "
b10000000 !
$end
#5
b1000000 !
b1000000 %
b1 "
b1 $
b1 #
#10
b100000 !
b100000 %
b10 "
b10 $
b10 #
#15
b10000 !
b10000 %
b11 "
b11 $
b11 #
#20
b1000 !
b1000 %
b100 "
b100 $
b100 #
#25
b100 !
b100 %
b101 "
b101 $
b101 #
#30
b10 !
b10 %
b110 "
b110 $
b110 #
#35
b1 !
b1 %
b111 "
b111 $
b111 #
#40
b1000 #
