day_04/code_converters/binary_to_excess-3/binary_to_excess-3.v
module binary_to_excess_3(
     input [3:0]b,
     output reg [3:0]x);
 
     always@(*)begin
        x = b + 4'd3;
      end
   endmodule

day_04/code_converters/binary_to_excess-3/binary_to_excess-3_tb.v
module binary_to_excess_3_tb();
       reg [3:0]b;
       wire [3:0]x;
       integer i;
       binary_to_excess_3 inst(b,x);
       initial begin
       $monitor("time=%0t|b=%b|x=%b",$time,b,x);
       $dumpfile("binary_to_excess-3.vcd");
       $dumpvars;
       b=4'b0000;
       for(i=0;i<16;i++)begin
        b=i;
        #5;
       end
       end
endmodule

day_04/code_converters/binary_to_excess-3/binary_to_excess-3.vcd
$date
	Mon Oct 13 20:29:14 2025
$end
$version
	Icarus Verilog
$end
$timescale
	1s
$end
$scope module binary_to_excess_3_tb $end
$var wire 4 ! x [3:0] $end
$var reg 4 " b [3:0] $end
$var integer 32 # i [31:0] $end
$scope module inst $end
$var wire 4 $ b [3:0] $end
$var reg 4 % x [3:0] $end
$upscope $end
$upscope $end
$enddefinitions $end
$comment Show the parameter values. $end
$dumpall
$end
#0
$dumpvars
b11 %
b0 $
b0 #
b0 "
b11 !
$end
#5
b100 !
b100 %
b1 "
b1 $
b1 #
#10
b101 !
b101 %
b10 "
b10 $
b10 #
#15
b110 !
b110 %
b11 "
b11 $
b11 #
#20
b111 !
b111 %
b100 "
b100 $
b100 #
#25
b1000 !
b1000 %
b101 "
b101 $
b101 #
#30
b1001 !
b1001 %
b110 "
b110 $
b110 #
#35
b1010 !
b1010 %
b111 "
b111 $
b111 #
#40
b1011 !
b1011 %
b1000 "
b1000 $
b1000 #
#45
b1100 !
b1100 %
b1001 "
b1001 $
b1001 #
#50
b1101 !
b1101 %
b1010 "
b1010 $
b1010 #
#55
b1110 !
b1110 %
b1011 "
b1011 $
b1011 #
#60
b1111 !
b1111 %
b1100 "
b1100 $
b1100 #
#65
b0 !
b0 %
b1101 "
b1101 $
b1101 #
#70
b1 !
b1 %
b1110 "
b1110 $
b1110 #
#75
b10 !
b10 %
b1111 "
b1111 $
b1111 #
#80
b10000 #
