day_01/mux/mux_8x1/mux_8x1.v
module mux_8x1(
	input [7:0]a,
	input [2:0]s,
	output reg y);
       always@(*)begin
        case(s)
           3'b000:y=a[0];
	   3'b001:y=a[1]; 
	   3'b010:y=a[2]; 
	   3'b011:y=a[3]; 
	   3'b100:y=a[4]; 
	   3'b101:y=a[5]; 
	   3'b110:y=a[6]; 
	   3'b111:y=a[7];
	   default: y=1'b0;
        endcase
       end
endmodule

day_01/mux/mux_8x1/mux_8x1_tb.v
module mux_8x1_tb();
   reg [7:0]a;
   reg [2:0]s;
   wire y;
   mux_8x1 inst(a,s,y);
   integer i;
   initial begin
   $monitor("time=%0t|a=%b|s=%b|y=%b",$time,a,s,y);
   $dumpfile("mux_8x1.vcd");
   $dumpvars;
   a=8'b01010110;
   for(i=0;i<8;i++)begin
     s=i;
     #5;
    end
   end
endmodule

day_01/mux/mux_8x1/mux_8x1.vcd
$date
	Mon Oct 13 16:05:23 2025
$end
$version
	Icarus Verilog
$end
$timescale
	1s
$end
$scope module mux_8x1_tb $end
$var wire 1 ! y $end
$var reg 8 " a [7:0] $end
$var reg 3 # s [2:0] $end
$var integer 32 $ i [31:0] $end
$scope module inst $end
$var wire 8 % a [7:0] $end
$var wire 3 & s [2:0] $end
$var reg 1 ! y $end
$upscope $end
$upscope $end
$enddefinitions $end
$comment Show the parameter values. $end
$dumpall
$end
#0
$dumpvars
b0 &
b1010110 %
b0 $
b0 #
b1010110 "
0!
$end
#5
1!
b1 #
b1 &
b1 $
#10
b10 #
b10 &
b10 $
#15
0!
b11 #
b11 &
b11 $
#20
1!
b100 #
b100 &
b100 $
#25
0!
b101 #
b101 &
b101 $
#30
1!
b110 #
b110 &
b110 $
#35
0!
b111 #
b111 &
b111 $
#40
b1000 $
