day_04/CLA/CLA.v
module carry_lookahead_adder(
     input [3:0]a,
     input [3:0]b,
     input cin,
     output reg sum,
     output reg cout);
    
    reg [3:0]p;
    reg [3:0]g;
    reg [4:0]c;
    integer i;
    
    always@(*)begin
       
      c[0] =cin;
      p = a&b;
      g = a^b;
      
    for(i=0;i<16;i++)begin
          c[i+1] = g[i] | (p[i] & c[i]);
       end
 
    for(i=0;i<16;i++)begin
         sum= p[i] ^ c[i];
       end
      cout = c[4];    
end
endmodule

day_04/CLA/CLA_tb.v
module carry_lookahead_adder_tb();
      reg [3:0]a;
      reg [3:0]b;
      reg cin;
      wire sum;
      wire cout;
      integer i, j;
    carry_lookahead_adder inst(a,b,cin,sum,cout);
       
      initial begin
      $monitor("time=%0t|a=%b|b=%b|sum=%b|cout=%b",$time,a,b,cin,sum,cout);
      $dumpfile("CLA.vcd");
      $dumpvars;
      
      cin=0;
      for(i=0;i<16;i++)begin
         for(j=0;j<16;j++)begin
            a=i;b=j;
            #5;
         end
       end
      cin=1;
      for(i=0;i<16;i++)begin                                                                                                                                         for(j=0;j<16;j++)begin                                                                                                                                         a=i;b=j;                                                                                                                                                    #5;                                                                                                                                                      end                                                                                                                                                       end
      $finish;
     end
endmodule

day_04/CLA/CLA.vcd
$date
	Tue Oct 14 16:27:30 2025
$end
$version
	Icarus Verilog
$end
$timescale
	1s
$end
$scope module carry_lookahead_adder_tb $end
$var wire 1 ! sum $end
$var wire 1 " cout $end
$var reg 4 # a [3:0] $end
$var reg 4 $ b [3:0] $end
$var reg 1 % cin $end
$var integer 32 & i [31:0] $end
$var integer 32 ' j [31:0] $end
$scope module inst $end
$var wire 4 ( a [3:0] $end
$var wire 4 ) b [3:0] $end
$var wire 1 % cin $end
$var reg 5 * c [4:0] $end
$var reg 1 " cout $end
$var reg 4 + g [3:0] $end
$var reg 4 , p [3:0] $end
$var reg 1 ! sum $end
$var integer 32 - i [31:0] $end
$upscope $end
$upscope $end
$enddefinitions $end
$comment Show the parameter values. $end
$dumpall
$end
#0
$dumpvars
b10000 -
b0 ,
b0 +
b0 *
b0 )
b0 (
b0 '
b0 &
0%
b0 $
b0 #
0"
x!
$end
#5
x!
b10 *
b10000 -
b1 +
b1 $
b1 )
b1 '
#10
x!
b100 *
b10000 -
b10 +
b10 $
b10 )
b10 '
#15
x!
b110 *
b10000 -
b11 +
b11 $
b11 )
b11 '
#20
x!
b1000 *
b10000 -
b100 +
b100 $
b100 )
b100 '
#25
x!
b1010 *
b10000 -
b101 +
b101 $
b101 )
b101 '
#30
x!
b1100 *
b10000 -
b110 +
b110 $
b110 )
b110 '
#35
x!
b1110 *
b10000 -
b111 +
b111 $
b111 )
b111 '
#40
1"
x!
b10000 *
b10000 -
b1000 +
b1000 $
b1000 )
b1000 '
#45
x!
b10010 *
b10000 -
b1001 +
b1001 $
b1001 )
b1001 '
#50
x!
b10100 *
b10000 -
b1010 +
b1010 $
b1010 )
b1010 '
#55
x!
b10110 *
b10000 -
b1011 +
b1011 $
b1011 )
b1011 '
#60
x!
b11000 *
b10000 -
b1100 +
b1100 $
b1100 )
b1100 '
#65
x!
b11010 *
b10000 -
b1101 +
b1101 $
b1101 )
b1101 '
#70
x!
b11100 *
b10000 -
b1110 +
b1110 $
b1110 )
b1110 '
#75
x!
b11110 *
b10000 -
b1111 +
b1111 $
b1111 )
b1111 '
#80
0"
x!
b10 *
b10000 -
b1 +
b0 $
b0 )
b1 #
b1 (
b1 &
b0 '
#85
x!
b0 *
b10000 -
b0 +
b1 ,
b1 $
b1 )
b1 '
#90
x!
b110 *
b10000 -
b11 +
b0 ,
b10 $
b10 )
b10 '
#95
x!
b100 *
b10000 -
b10 +
b1 ,
b11 $
b11 )
b11 '
#100
x!
b1010 *
b10000 -
b101 +
b0 ,
b100 $
b100 )
b100 '
#105
x!
b1000 *
b10000 -
b100 +
b1 ,
b101 $
b101 )
b101 '
#110
x!
b1110 *
b10000 -
b111 +
b0 ,
b110 $
b110 )
b110 '
#115
x!
b1100 *
b10000 -
b110 +
b1 ,
b111 $
b111 )
b111 '
#120
1"
x!
b10010 *
b10000 -
b1001 +
b0 ,
b1000 $
b1000 )
b1000 '
#125
x!
b10000 *
b10000 -
b1000 +
b1 ,
b1001 $
b1001 )
b1001 '
#130
x!
b10110 *
b10000 -
b1011 +
b0 ,
b1010 $
b1010 )
b1010 '
#135
x!
b10100 *
b10000 -
b1010 +
b1 ,
b1011 $
b1011 )
b1011 '
#140
x!
b11010 *
b10000 -
b1101 +
b0 ,
b1100 $
b1100 )
b1100 '
#145
x!
b11000 *
b10000 -
b1100 +
b1 ,
b1101 $
b1101 )
b1101 '
#150
x!
b11110 *
b10000 -
b1111 +
b0 ,
b1110 $
b1110 )
b1110 '
#155
x!
b11100 *
b10000 -
b1110 +
b1 ,
b1111 $
b1111 )
b1111 '
#160
0"
x!
b100 *
b10000 -
b10 +
b0 ,
b0 $
b0 )
b10 #
b10 (
b10 &
b0 '
#165
x!
b110 *
b10000 -
b11 +
b1 $
b1 )
b1 '
#170
x!
b0 *
b10000 -
b0 +
b10 ,
b10 $
b10 )
b10 '
#175
x!
b110 *
b10000 -
b1 +
b11 $
b11 )
b11 '
#180
x!
b1100 *
b10000 -
b110 +
b0 ,
b100 $
b100 )
b100 '
#185
x!
b1110 *
b10000 -
b111 +
b101 $
b101 )
b101 '
#190
x!
b1000 *
b10000 -
b100 +
b10 ,
b110 $
b110 )
b110 '
#195
x!
b1110 *
b10000 -
b101 +
b111 $
b111 )
b111 '
#200
1"
x!
b10100 *
b10000 -
b1010 +
b0 ,
b1000 $
b1000 )
b1000 '
#205
x!
b10110 *
b10000 -
b1011 +
b1001 $
b1001 )
b1001 '
#210
x!
b10000 *
b10000 -
b1000 +
b10 ,
b1010 $
b1010 )
b1010 '
#215
x!
b10110 *
b10000 -
b1001 +
b1011 $
b1011 )
b1011 '
#220
x!
b11100 *
b10000 -
b1110 +
b0 ,
b1100 $
b1100 )
b1100 '
#225
x!
b11110 *
b10000 -
b1111 +
b1101 $
b1101 )
b1101 '
#230
x!
b11000 *
b10000 -
b1100 +
b10 ,
b1110 $
b1110 )
b1110 '
#235
x!
b11110 *
b10000 -
b1101 +
b1111 $
b1111 )
b1111 '
#240
0"
x!
b110 *
b10000 -
b11 +
b0 ,
b0 $
b0 )
b11 #
b11 (
b11 &
b0 '
#245
x!
b100 *
b10000 -
b10 +
b1 ,
b1 $
b1 )
b1 '
#250
x!
b110 *
b10000 -
b1 +
b10 ,
b10 $
b10 )
b10 '
#255
x!
b0 *
b10000 -
b0 +
b11 ,
b11 $
b11 )
b11 '
#260
x!
b1110 *
b10000 -
b111 +
b0 ,
b100 $
b100 )
b100 '
#265
x!
b1100 *
b10000 -
b110 +
b1 ,
b101 $
b101 )
b101 '
#270
x!
b1110 *
b10000 -
b101 +
b10 ,
b110 $
b110 )
b110 '
#275
x!
b1000 *
b10000 -
b100 +
b11 ,
b111 $
b111 )
b111 '
#280
1"
x!
b10110 *
b10000 -
b1011 +
b0 ,
b1000 $
b1000 )
b1000 '
#285
x!
b10100 *
b10000 -
b1010 +
b1 ,
b1001 $
b1001 )
b1001 '
#290
x!
b10110 *
b10000 -
b1001 +
b10 ,
b1010 $
b1010 )
b1010 '
#295
x!
b10000 *
b10000 -
b1000 +
b11 ,
b1011 $
b1011 )
b1011 '
#300
x!
b11110 *
b10000 -
b1111 +
b0 ,
b1100 $
b1100 )
b1100 '
#305
x!
b11100 *
b10000 -
b1110 +
b1 ,
b1101 $
b1101 )
b1101 '
#310
x!
b11110 *
b10000 -
b1101 +
b10 ,
b1110 $
b1110 )
b1110 '
#315
x!
b11000 *
b10000 -
b1100 +
b11 ,
b1111 $
b1111 )
b1111 '
#320
0"
x!
b1000 *
b10000 -
b100 +
b0 ,
b0 $
b0 )
b100 #
b100 (
b100 &
b0 '
#325
x!
b1010 *
b10000 -
b101 +
b1 $
b1 )
b1 '
#330
x!
b1100 *
b10000 -
b110 +
b10 $
b10 )
b10 '
#335
x!
b1110 *
b10000 -
b111 +
b11 $
b11 )
b11 '
#340
x!
b0 *
b10000 -
b0 +
b100 ,
b100 $
b100 )
b100 '
#345
x!
b10 *
b10000 -
b1 +
b101 $
b101 )
b101 '
#350
x!
b1100 *
b10000 -
b10 +
b110 $
b110 )
b110 '
#355
x!
b1110 *
b10000 -
b11 +
b111 $
b111 )
b111 '
#360
1"
x!
b11000 *
b10000 -
b1100 +
b0 ,
b1000 $
b1000 )
b1000 '
#365
x!
b11010 *
b10000 -
b1101 +
b1001 $
b1001 )
b1001 '
#370
x!
b11100 *
b10000 -
b1110 +
b1010 $
b1010 )
b1010 '
#375
x!
b11110 *
b10000 -
b1111 +
b1011 $
b1011 )
b1011 '
#380
x!
b10000 *
b10000 -
b1000 +
b100 ,
b1100 $
b1100 )
b1100 '
#385
x!
b10010 *
b10000 -
b1001 +
b1101 $
b1101 )
b1101 '
#390
x!
b11100 *
b10000 -
b1010 +
b1110 $
b1110 )
b1110 '
#395
x!
b11110 *
b10000 -
b1011 +
b1111 $
b1111 )
b1111 '
#400
0"
x!
b1010 *
b10000 -
b101 +
b0 ,
b0 $
b0 )
b101 #
b101 (
b101 &
b0 '
#405
x!
b1000 *
b10000 -
b100 +
b1 ,
b1 $
b1 )
b1 '
#410
x!
b1110 *
b10000 -
b111 +
b0 ,
b10 $
b10 )
b10 '
#415
x!
b1100 *
b10000 -
b110 +
b1 ,
b11 $
b11 )
b11 '
#420
x!
b10 *
b10000 -
b1 +
b100 ,
b100 $
b100 )
b100 '
#425
x!
b0 *
b10000 -
b0 +
b101 ,
b101 $
b101 )
b101 '
#430
x!
b1110 *
b10000 -
b11 +
b100 ,
b110 $
b110 )
b110 '
#435
x!
b1100 *
b10000 -
b10 +
b101 ,
b111 $
b111 )
b111 '
#440
1"
x!
b11010 *
b10000 -
b1101 +
b0 ,
b1000 $
b1000 )
b1000 '
#445
x!
b11000 *
b10000 -
b1100 +
b1 ,
b1001 $
b1001 )
b1001 '
#450
x!
b11110 *
b10000 -
b1111 +
b0 ,
b1010 $
b1010 )
b1010 '
#455
x!
b11100 *
b10000 -
b1110 +
b1 ,
b1011 $
b1011 )
b1011 '
#460
x!
b10010 *
b10000 -
b1001 +
b100 ,
b1100 $
b1100 )
b1100 '
#465
x!
b10000 *
b10000 -
b1000 +
b101 ,
b1101 $
b1101 )
b1101 '
#470
x!
b11110 *
b10000 -
b1011 +
b100 ,
b1110 $
b1110 )
b1110 '
#475
x!
b11100 *
b10000 -
b1010 +
b101 ,
b1111 $
b1111 )
b1111 '
#480
0"
x!
b1100 *
b10000 -
b110 +
b0 ,
b0 $
b0 )
b110 #
b110 (
b110 &
b0 '
#485
x!
b1110 *
b10000 -
b111 +
b1 $
b1 )
b1 '
#490
x!
b1000 *
b10000 -
b100 +
b10 ,
b10 $
b10 )
b10 '
#495
x!
b1110 *
b10000 -
b101 +
b11 $
b11 )
b11 '
#500
x!
b1100 *
b10000 -
b10 +
b100 ,
b100 $
b100 )
b100 '
#505
x!
b1110 *
b10000 -
b11 +
b101 $
b101 )
b101 '
#510
x!
b0 *
b10000 -
b0 +
b110 ,
b110 $
b110 )
b110 '
#515
x!
b1110 *
b10000 -
b1 +
b111 $
b111 )
b111 '
#520
1"
x!
b11100 *
b10000 -
b1110 +
b0 ,
b1000 $
b1000 )
b1000 '
#525
x!
b11110 *
b10000 -
b1111 +
b1001 $
b1001 )
b1001 '
#530
x!
b11000 *
b10000 -
b1100 +
b10 ,
b1010 $
b1010 )
b1010 '
#535
x!
b11110 *
b10000 -
b1101 +
b1011 $
b1011 )
b1011 '
#540
x!
b11100 *
b10000 -
b1010 +
b100 ,
b1100 $
b1100 )
b1100 '
#545
x!
b11110 *
b10000 -
b1011 +
b1101 $
b1101 )
b1101 '
#550
x!
b10000 *
b10000 -
b1000 +
b110 ,
b1110 $
b1110 )
b1110 '
#555
x!
b11110 *
b10000 -
b1001 +
b1111 $
b1111 )
b1111 '
#560
0"
x!
b1110 *
b10000 -
b111 +
b0 ,
b0 $
b0 )
b111 #
b111 (
b111 &
b0 '
#565
x!
b1100 *
b10000 -
b110 +
b1 ,
b1 $
b1 )
b1 '
#570
x!
b1110 *
b10000 -
b101 +
b10 ,
b10 $
b10 )
b10 '
#575
x!
b1000 *
b10000 -
b100 +
b11 ,
b11 $
b11 )
b11 '
#580
x!
b1110 *
b10000 -
b11 +
b100 ,
b100 $
b100 )
b100 '
#585
x!
b1100 *
b10000 -
b10 +
b101 ,
b101 $
b101 )
b101 '
#590
x!
b1110 *
b10000 -
b1 +
b110 ,
b110 $
b110 )
b110 '
#595
x!
b0 *
b10000 -
b0 +
b111 ,
b111 $
b111 )
b111 '
#600
1"
x!
b11110 *
b10000 -
b1111 +
b0 ,
b1000 $
b1000 )
b1000 '
#605
x!
b11100 *
b10000 -
b1110 +
b1 ,
b1001 $
b1001 )
b1001 '
#610
x!
b11110 *
b10000 -
b1101 +
b10 ,
b1010 $
b1010 )
b1010 '
#615
x!
b11000 *
b10000 -
b1100 +
b11 ,
b1011 $
b1011 )
b1011 '
#620
x!
b11110 *
b10000 -
b1011 +
b100 ,
b1100 $
b1100 )
b1100 '
#625
x!
b11100 *
b10000 -
b1010 +
b101 ,
b1101 $
b1101 )
b1101 '
#630
x!
b11110 *
b10000 -
b1001 +
b110 ,
b1110 $
b1110 )
b1110 '
#635
x!
b10000 *
b10000 -
b1000 +
b111 ,
b1111 $
b1111 )
b1111 '
#640
x!
b10000 -
b0 ,
b0 $
b0 )
b1000 #
b1000 (
b1000 &
b0 '
#645
x!
b10010 *
b10000 -
b1001 +
b1 $
b1 )
b1 '
#650
x!
b10100 *
b10000 -
b1010 +
b10 $
b10 )
b10 '
#655
x!
b10110 *
b10000 -
b1011 +
b11 $
b11 )
b11 '
#660
x!
b11000 *
b10000 -
b1100 +
b100 $
b100 )
b100 '
#665
x!
b11010 *
b10000 -
b1101 +
b101 $
b101 )
b101 '
#670
x!
b11100 *
b10000 -
b1110 +
b110 $
b110 )
b110 '
#675
x!
b11110 *
b10000 -
b1111 +
b111 $
b111 )
b111 '
#680
0"
x!
b0 *
b10000 -
b0 +
b1000 ,
b1000 $
b1000 )
b1000 '
#685
x!
b10 *
b10000 -
b1 +
b1001 $
b1001 )
b1001 '
#690
x!
b100 *
b10000 -
b10 +
b1010 $
b1010 )
b1010 '
#695
x!
b110 *
b10000 -
b11 +
b1011 $
b1011 )
b1011 '
#700
1"
x!
b11000 *
b10000 -
b100 +
b1100 $
b1100 )
b1100 '
#705
x!
b11010 *
b10000 -
b101 +
b1101 $
b1101 )
b1101 '
#710
x!
b11100 *
b10000 -
b110 +
b1110 $
b1110 )
b1110 '
#715
x!
b11110 *
b10000 -
b111 +
b1111 $
b1111 )
b1111 '
#720
x!
b10010 *
b10000 -
b1001 +
b0 ,
b0 $
b0 )
b1001 #
b1001 (
b1001 &
b0 '
#725
x!
b10000 *
b10000 -
b1000 +
b1 ,
b1 $
b1 )
b1 '
#730
x!
b10110 *
b10000 -
b1011 +
b0 ,
b10 $
b10 )
b10 '
#735
x!
b10100 *
b10000 -
b1010 +
b1 ,
b11 $
b11 )
b11 '
#740
x!
b11010 *
b10000 -
b1101 +
b0 ,
b100 $
b100 )
b100 '
#745
x!
b11000 *
b10000 -
b1100 +
b1 ,
b101 $
b101 )
b101 '
#750
x!
b11110 *
b10000 -
b1111 +
b0 ,
b110 $
b110 )
b110 '
#755
x!
b11100 *
b10000 -
b1110 +
b1 ,
b111 $
b111 )
b111 '
#760
0"
x!
b10 *
b10000 -
b1 +
b1000 ,
b1000 $
b1000 )
b1000 '
#765
x!
b0 *
b10000 -
b0 +
b1001 ,
b1001 $
b1001 )
b1001 '
#770
x!
b110 *
b10000 -
b11 +
b1000 ,
b1010 $
b1010 )
b1010 '
#775
x!
b100 *
b10000 -
b10 +
b1001 ,
b1011 $
b1011 )
b1011 '
#780
1"
x!
b11010 *
b10000 -
b101 +
b1000 ,
b1100 $
b1100 )
b1100 '
#785
x!
b11000 *
b10000 -
b100 +
b1001 ,
b1101 $
b1101 )
b1101 '
#790
x!
b11110 *
b10000 -
b111 +
b1000 ,
b1110 $
b1110 )
b1110 '
#795
x!
b11100 *
b10000 -
b110 +
b1001 ,
b1111 $
b1111 )
b1111 '
#800
x!
b10100 *
b10000 -
b1010 +
b0 ,
b0 $
b0 )
b1010 #
b1010 (
b1010 &
b0 '
#805
x!
b10110 *
b10000 -
b1011 +
b1 $
b1 )
b1 '
#810
x!
b10000 *
b10000 -
b1000 +
b10 ,
b10 $
b10 )
b10 '
#815
x!
b10110 *
b10000 -
b1001 +
b11 $
b11 )
b11 '
#820
x!
b11100 *
b10000 -
b1110 +
b0 ,
b100 $
b100 )
b100 '
#825
x!
b11110 *
b10000 -
b1111 +
b101 $
b101 )
b101 '
#830
x!
b11000 *
b10000 -
b1100 +
b10 ,
b110 $
b110 )
b110 '
#835
x!
b11110 *
b10000 -
b1101 +
b111 $
b111 )
b111 '
#840
0"
x!
b100 *
b10000 -
b10 +
b1000 ,
b1000 $
b1000 )
b1000 '
#845
x!
b110 *
b10000 -
b11 +
b1001 $
b1001 )
b1001 '
#850
x!
b0 *
b10000 -
b0 +
b1010 ,
b1010 $
b1010 )
b1010 '
#855
x!
b110 *
b10000 -
b1 +
b1011 $
b1011 )
b1011 '
#860
1"
x!
b11100 *
b10000 -
b110 +
b1000 ,
b1100 $
b1100 )
b1100 '
#865
x!
b11110 *
b10000 -
b111 +
b1101 $
b1101 )
b1101 '
#870
x!
b11000 *
b10000 -
b100 +
b1010 ,
b1110 $
b1110 )
b1110 '
#875
x!
b11110 *
b10000 -
b101 +
b1111 $
b1111 )
b1111 '
#880
x!
b10110 *
b10000 -
b1011 +
b0 ,
b0 $
b0 )
b1011 #
b1011 (
b1011 &
b0 '
#885
x!
b10100 *
b10000 -
b1010 +
b1 ,
b1 $
b1 )
b1 '
#890
x!
b10110 *
b10000 -
b1001 +
b10 ,
b10 $
b10 )
b10 '
#895
x!
b10000 *
b10000 -
b1000 +
b11 ,
b11 $
b11 )
b11 '
#900
x!
b11110 *
b10000 -
b1111 +
b0 ,
b100 $
b100 )
b100 '
#905
x!
b11100 *
b10000 -
b1110 +
b1 ,
b101 $
b101 )
b101 '
#910
x!
b11110 *
b10000 -
b1101 +
b10 ,
b110 $
b110 )
b110 '
#915
x!
b11000 *
b10000 -
b1100 +
b11 ,
b111 $
b111 )
b111 '
#920
0"
x!
b110 *
b10000 -
b11 +
b1000 ,
b1000 $
b1000 )
b1000 '
#925
x!
b100 *
b10000 -
b10 +
b1001 ,
b1001 $
b1001 )
b1001 '
#930
x!
b110 *
b10000 -
b1 +
b1010 ,
b1010 $
b1010 )
b1010 '
#935
x!
b0 *
b10000 -
b0 +
b1011 ,
b1011 $
b1011 )
b1011 '
#940
1"
x!
b11110 *
b10000 -
b111 +
b1000 ,
b1100 $
b1100 )
b1100 '
#945
x!
b11100 *
b10000 -
b110 +
b1001 ,
b1101 $
b1101 )
b1101 '
#950
x!
b11110 *
b10000 -
b101 +
b1010 ,
b1110 $
b1110 )
b1110 '
#955
x!
b11000 *
b10000 -
b100 +
b1011 ,
b1111 $
b1111 )
b1111 '
#960
x!
b10000 -
b1100 +
b0 ,
b0 $
b0 )
b1100 #
b1100 (
b1100 &
b0 '
#965
x!
b11010 *
b10000 -
b1101 +
b1 $
b1 )
b1 '
#970
x!
b11100 *
b10000 -
b1110 +
b10 $
b10 )
b10 '
#975
x!
b11110 *
b10000 -
b1111 +
b11 $
b11 )
b11 '
#980
x!
b10000 *
b10000 -
b1000 +
b100 ,
b100 $
b100 )
b100 '
#985
x!
b10010 *
b10000 -
b1001 +
b101 $
b101 )
b101 '
#990
x!
b11100 *
b10000 -
b1010 +
b110 $
b110 )
b110 '
#995
x!
b11110 *
b10000 -
b1011 +
b111 $
b111 )
b111 '
#1000
x!
b11000 *
b10000 -
b100 +
b1000 ,
b1000 $
b1000 )
b1000 '
#1005
x!
b11010 *
b10000 -
b101 +
b1001 $
b1001 )
b1001 '
#1010
x!
b11100 *
b10000 -
b110 +
b1010 $
b1010 )
b1010 '
#1015
x!
b11110 *
b10000 -
b111 +
b1011 $
b1011 )
b1011 '
#1020
0"
x!
b0 *
b10000 -
b0 +
b1100 ,
b1100 $
b1100 )
b1100 '
#1025
x!
b10 *
b10000 -
b1 +
b1101 $
b1101 )
b1101 '
#1030
1"
x!
b11100 *
b10000 -
b10 +
b1110 $
b1110 )
b1110 '
#1035
x!
b11110 *
b10000 -
b11 +
b1111 $
b1111 )
b1111 '
#1040
x!
b11010 *
b10000 -
b1101 +
b0 ,
b0 $
b0 )
b1101 #
b1101 (
b1101 &
b0 '
#1045
x!
b11000 *
b10000 -
b1100 +
b1 ,
b1 $
b1 )
b1 '
#1050
x!
b11110 *
b10000 -
b1111 +
b0 ,
b10 $
b10 )
b10 '
#1055
x!
b11100 *
b10000 -
b1110 +
b1 ,
b11 $
b11 )
b11 '
#1060
x!
b10010 *
b10000 -
b1001 +
b100 ,
b100 $
b100 )
b100 '
#1065
x!
b10000 *
b10000 -
b1000 +
b101 ,
b101 $
b101 )
b101 '
#1070
x!
b11110 *
b10000 -
b1011 +
b100 ,
b110 $
b110 )
b110 '
#1075
x!
b11100 *
b10000 -
b1010 +
b101 ,
b111 $
b111 )
b111 '
#1080
x!
b11010 *
b10000 -
b101 +
b1000 ,
b1000 $
b1000 )
b1000 '
#1085
x!
b11000 *
b10000 -
b100 +
b1001 ,
b1001 $
b1001 )
b1001 '
#1090
x!
b11110 *
b10000 -
b111 +
b1000 ,
b1010 $
b1010 )
b1010 '
#1095
x!
b11100 *
b10000 -
b110 +
b1001 ,
b1011 $
b1011 )
b1011 '
#1100
0"
x!
b10 *
b10000 -
b1 +
b1100 ,
b1100 $
b1100 )
b1100 '
#1105
x!
b0 *
b10000 -
b0 +
b1101 ,
b1101 $
b1101 )
b1101 '
#1110
1"
x!
b11110 *
b10000 -
b11 +
b1100 ,
b1110 $
b1110 )
b1110 '
#1115
x!
b11100 *
b10000 -
b10 +
b1101 ,
b1111 $
b1111 )
b1111 '
#1120
x!
b10000 -
b1110 +
b0 ,
b0 $
b0 )
b1110 #
b1110 (
b1110 &
b0 '
#1125
x!
b11110 *
b10000 -
b1111 +
b1 $
b1 )
b1 '
#1130
x!
b11000 *
b10000 -
b1100 +
b10 ,
b10 $
b10 )
b10 '
#1135
x!
b11110 *
b10000 -
b1101 +
b11 $
b11 )
b11 '
#1140
x!
b11100 *
b10000 -
b1010 +
b100 ,
b100 $
b100 )
b100 '
#1145
x!
b11110 *
b10000 -
b1011 +
b101 $
b101 )
b101 '
#1150
x!
b10000 *
b10000 -
b1000 +
b110 ,
b110 $
b110 )
b110 '
#1155
x!
b11110 *
b10000 -
b1001 +
b111 $
b111 )
b111 '
#1160
x!
b11100 *
b10000 -
b110 +
b1000 ,
b1000 $
b1000 )
b1000 '
#1165
x!
b11110 *
b10000 -
b111 +
b1001 $
b1001 )
b1001 '
#1170
x!
b11000 *
b10000 -
b100 +
b1010 ,
b1010 $
b1010 )
b1010 '
#1175
x!
b11110 *
b10000 -
b101 +
b1011 $
b1011 )
b1011 '
#1180
x!
b11100 *
b10000 -
b10 +
b1100 ,
b1100 $
b1100 )
b1100 '
#1185
x!
b11110 *
b10000 -
b11 +
b1101 $
b1101 )
b1101 '
#1190
0"
x!
b0 *
b10000 -
b0 +
b1110 ,
b1110 $
b1110 )
b1110 '
#1195
1"
x!
b11110 *
b10000 -
b1 +
b1111 $
b1111 )
b1111 '
#1200
x!
b10000 -
b1111 +
b0 ,
b0 $
b0 )
b1111 #
b1111 (
b1111 &
b0 '
#1205
x!
b11100 *
b10000 -
b1110 +
b1 ,
b1 $
b1 )
b1 '
#1210
x!
b11110 *
b10000 -
b1101 +
b10 ,
b10 $
b10 )
b10 '
#1215
x!
b11000 *
b10000 -
b1100 +
b11 ,
b11 $
b11 )
b11 '
#1220
x!
b11110 *
b10000 -
b1011 +
b100 ,
b100 $
b100 )
b100 '
#1225
x!
b11100 *
b10000 -
b1010 +
b101 ,
b101 $
b101 )
b101 '
#1230
x!
b11110 *
b10000 -
b1001 +
b110 ,
b110 $
b110 )
b110 '
#1235
x!
b10000 *
b10000 -
b1000 +
b111 ,
b111 $
b111 )
b111 '
#1240
x!
b11110 *
b10000 -
b111 +
b1000 ,
b1000 $
b1000 )
b1000 '
#1245
x!
b11100 *
b10000 -
b110 +
b1001 ,
b1001 $
b1001 )
b1001 '
#1250
x!
b11110 *
b10000 -
b101 +
b1010 ,
b1010 $
b1010 )
b1010 '
#1255
x!
b11000 *
b10000 -
b100 +
b1011 ,
b1011 $
b1011 )
b1011 '
#1260
x!
b11110 *
b10000 -
b11 +
b1100 ,
b1100 $
b1100 )
b1100 '
#1265
x!
b11100 *
b10000 -
b10 +
b1101 ,
b1101 $
b1101 )
b1101 '
#1270
x!
b11110 *
b10000 -
b1 +
b1110 ,
b1110 $
b1110 )
b1110 '
#1275
0"
x!
b0 *
b10000 -
b0 +
b1111 ,
b1111 $
b1111 )
b1111 '
#1280
x!
b10000 -
b0 ,
b1 *
b0 $
b0 )
b0 #
b0 (
1%
b0 &
b0 '
#1285
x!
b11 *
b10000 -
b1 +
b1 $
b1 )
b1 '
#1290
x!
b101 *
b10000 -
b10 +
b10 $
b10 )
b10 '
#1295
x!
b111 *
b10000 -
b11 +
b11 $
b11 )
b11 '
#1300
x!
b1001 *
b10000 -
b100 +
b100 $
b100 )
b100 '
#1305
x!
b1011 *
b10000 -
b101 +
b101 $
b101 )
b101 '
#1310
x!
b1101 *
b10000 -
b110 +
b110 $
b110 )
b110 '
#1315
x!
b1111 *
b10000 -
b111 +
b111 $
b111 )
b111 '
#1320
1"
x!
b10001 *
b10000 -
b1000 +
b1000 $
b1000 )
b1000 '
#1325
x!
b10011 *
b10000 -
b1001 +
b1001 $
b1001 )
b1001 '
#1330
x!
b10101 *
b10000 -
b1010 +
b1010 $
b1010 )
b1010 '
#1335
x!
b10111 *
b10000 -
b1011 +
b1011 $
b1011 )
b1011 '
#1340
x!
b11001 *
b10000 -
b1100 +
b1100 $
b1100 )
b1100 '
#1345
x!
b11011 *
b10000 -
b1101 +
b1101 $
b1101 )
b1101 '
#1350
x!
b11101 *
b10000 -
b1110 +
b1110 $
b1110 )
b1110 '
#1355
x!
b11111 *
b10000 -
b1111 +
b1111 $
b1111 )
b1111 '
#1360
0"
x!
b11 *
b10000 -
b1 +
b0 $
b0 )
b1 #
b1 (
b1 &
b0 '
#1365
x!
b10000 -
b0 +
b1 ,
b1 $
b1 )
b1 '
#1370
x!
b111 *
b10000 -
b11 +
b0 ,
b10 $
b10 )
b10 '
#1375
x!
b10000 -
b10 +
b1 ,
b11 $
b11 )
b11 '
#1380
x!
b1011 *
b10000 -
b101 +
b0 ,
b100 $
b100 )
b100 '
#1385
x!
b10000 -
b100 +
b1 ,
b101 $
b101 )
b101 '
#1390
x!
b1111 *
b10000 -
b111 +
b0 ,
b110 $
b110 )
b110 '
#1395
x!
b10000 -
b110 +
b1 ,
b111 $
b111 )
b111 '
#1400
1"
x!
b10011 *
b10000 -
b1001 +
b0 ,
b1000 $
b1000 )
b1000 '
#1405
x!
b10000 -
b1000 +
b1 ,
b1001 $
b1001 )
b1001 '
#1410
x!
b10111 *
b10000 -
b1011 +
b0 ,
b1010 $
b1010 )
b1010 '
#1415
x!
b10000 -
b1010 +
b1 ,
b1011 $
b1011 )
b1011 '
#1420
x!
b11011 *
b10000 -
b1101 +
b0 ,
b1100 $
b1100 )
b1100 '
#1425
x!
b10000 -
b1100 +
b1 ,
b1101 $
b1101 )
b1101 '
#1430
x!
b11111 *
b10000 -
b1111 +
b0 ,
b1110 $
b1110 )
b1110 '
#1435
x!
b10000 -
b1110 +
b1 ,
b1111 $
b1111 )
b1111 '
#1440
0"
x!
b101 *
b10000 -
b10 +
b0 ,
b0 $
b0 )
b10 #
b10 (
b10 &
b0 '
#1445
x!
b111 *
b10000 -
b11 +
b1 $
b1 )
b1 '
#1450
x!
b1 *
b10000 -
b0 +
b10 ,
b10 $
b10 )
b10 '
#1455
x!
b111 *
b10000 -
b1 +
b11 $
b11 )
b11 '
#1460
x!
b1101 *
b10000 -
b110 +
b0 ,
b100 $
b100 )
b100 '
#1465
x!
b1111 *
b10000 -
b111 +
b101 $
b101 )
b101 '
#1470
x!
b1001 *
b10000 -
b100 +
b10 ,
b110 $
b110 )
b110 '
#1475
x!
b1111 *
b10000 -
b101 +
b111 $
b111 )
b111 '
#1480
1"
x!
b10101 *
b10000 -
b1010 +
b0 ,
b1000 $
b1000 )
b1000 '
#1485
x!
b10111 *
b10000 -
b1011 +
b1001 $
b1001 )
b1001 '
#1490
x!
b10001 *
b10000 -
b1000 +
b10 ,
b1010 $
b1010 )
b1010 '
#1495
x!
b10111 *
b10000 -
b1001 +
b1011 $
b1011 )
b1011 '
#1500
x!
b11101 *
b10000 -
b1110 +
b0 ,
b1100 $
b1100 )
b1100 '
#1505
x!
b11111 *
b10000 -
b1111 +
b1101 $
b1101 )
b1101 '
#1510
x!
b11001 *
b10000 -
b1100 +
b10 ,
b1110 $
b1110 )
b1110 '
#1515
x!
b11111 *
b10000 -
b1101 +
b1111 $
b1111 )
b1111 '
#1520
0"
x!
b111 *
b10000 -
b11 +
b0 ,
b0 $
b0 )
b11 #
b11 (
b11 &
b0 '
#1525
x!
b10000 -
b10 +
b1 ,
b1 $
b1 )
b1 '
#1530
x!
b10000 -
b1 +
b10 ,
b10 $
b10 )
b10 '
#1535
x!
b10000 -
b0 +
b11 ,
b11 $
b11 )
b11 '
