day_02/demux/demux_1x8/demux_1x8.v
module demux_1x8(
   input a,
   input [2:0] s,
   output y0,y1,y2,y3,y4,y5,y6,y7);

   assign y0 = (~s[2] & ~s[1] & ~s[0]) & a;
   assign y1 = (~s[2] & ~s[1] &  s[0]) & a;
   assign y2 = (~s[2] &  s[1] & ~s[0]) & a;
   assign y3 = (~s[2] &  s[1] &  s[0]) & a;
   assign y4 = ( s[2] & ~s[1] & ~s[0]) & a;
   assign y5 = ( s[2] & ~s[1] &  s[0]) & a;
   assign y6 = ( s[2] &  s[1] & ~s[0]) & a;
   assign y7 = ( s[2] &  s[1] &  s[0]) & a;
endmodule

day_02/demux/demux_1x8/demux_1x8_tb.v
module demux_1x8_tb();
  reg a;
  reg [2:0] s;
  wire y0,y1,y2,y3,y4,y5,y6,y7;

 demux_1x8 inst(.a(a),.s(s),.y0(y0),.y1(y1),.y2(y2),.y3(y3),.y4(y4),.y5(y5),.y6(y6),.y7(y7));
   initial begin
     $monitor("time=%0t| a=%b| s=%b| y0=%b| y1=%b| y2=%b| y3=%b| y4=%b| y5=%b| y6=%b| y7=%b",$time,a,s,y0,y1,y2,y3,y4,y5,y6,y7);
     $dumpfile ("demux_1x8.vcd");
     $dumpvars;

     a=0; a=1;
     s=3'b000;#5;
     s=3'b001;#5;
     s=3'b010;#5;
     s=3'b011;#5;
     s=3'b100;#5;
     s=3'b101;#5;
     s=3'b110;#5;
     s=3'b111;#5;
     $finish;
    end
endmodule

day_02/demux/demux_1x8/demux_1x8.vcd
$date
	Fri Oct 10 20:41:01 2025
$end
$version
	Icarus Verilog
$end
$timescale
	1s
$end
$scope module demux_1x8_tb $end
$var wire 1 ! y7 $end
$var wire 1 " y6 $end
$var wire 1 # y5 $end
$var wire 1 $ y4 $end
$var wire 1 % y3 $end
$var wire 1 & y2 $end
$var wire 1 ' y1 $end
$var wire 1 ( y0 $end
$var reg 1 ) a $end
$var reg 3 * s [2:0] $end
$scope module inst $end
$var wire 1 ) a $end
$var wire 3 + s [2:0] $end
$var wire 1 ( y0 $end
$var wire 1 ' y1 $end
$var wire 1 & y2 $end
$var wire 1 % y3 $end
$var wire 1 $ y4 $end
$var wire 1 # y5 $end
$var wire 1 " y6 $end
$var wire 1 ! y7 $end
$upscope $end
$upscope $end
$enddefinitions $end
$comment Show the parameter values. $end
$dumpall
$end
#0
$dumpvars
b0 +
b0 *
1)
1(
0'
0&
0%
0$
0#
0"
0!
$end
#5
0(
1'
b1 *
b1 +
#10
0(
1&
0'
b10 *
b10 +
#15
0&
1%
b11 *
b11 +
#20
1$
0%
b100 *
b100 +
#25
0$
1#
b101 *
b101 +
#30
0$
1"
0#
b110 *
b110 +
#35
0"
1!
b111 *
b111 +
