day_04/code_converters/binary_to_7segment/binary_to_7segment.v
module binary_to_7segment(
      input [3:0]b,        // b represents binary
      output reg [6:0]s);  // s represents 7-segment
   
     always@(*)begin
         case(b)
        4'b0000:s=7'b1111110;
	4'b0001:s=7'b0110000;
	4'b0010:s=7'b1101101;
	4'b0011:s=7'b1111001;
	4'b0100:s=7'b0110011;
	4'b0101:s=7'b1011011;
	4'b0110:s=7'b1011111;
	4'b0111:s=7'b1110000;
	4'b1000:s=7'b1111111;
	4'b1001:s=7'b1111011;
	default: s = 7'b0000000;
      endcase
    end
endmodule

day_04/code_converters/binary_to_7segment/binary_to_7segment_tb.v
module binary_to_7segment_tb();
     reg [3:0]b;
     wire [6:0]s;
     integer i;
     binary_to_7segment inst(b,s);
     initial begin
     $monitor("time=%0t|b=%b|s=%b",$time,b,s);
     $dumpfile("binary_to_7segment.vcd");
     $dumpvars;
     for(i=0;i<10;i++)begin
       b=i;
       #5;
     end
    end
 endmodule

day_04/code_converters/binary_to_7segment/binary_to_7segment.vcd
$date
	Mon Oct 13 21:41:32 2025
$end
$version
	Icarus Verilog
$end
$timescale
	1s
$end
$scope module binary_to_7segment_tb $end
$var wire 7 ! s [6:0] $end
$var reg 4 " b [3:0] $end
$var integer 32 # i [31:0] $end
$scope module inst $end
$var wire 4 $ b [3:0] $end
$var reg 7 % s [6:0] $end
$upscope $end
$upscope $end
$enddefinitions $end
$comment Show the parameter values. $end
$dumpall
$end
#0
$dumpvars
b1111110 %
b0 $
b0 #
b0 "
b1111110 !
$end
#5
b110000 !
b110000 %
b1 "
b1 $
b1 #
#10
b1101101 !
b1101101 %
b10 "
b10 $
b10 #
#15
b1111001 !
b1111001 %
b11 "
b11 $
b11 #
#20
b110011 !
b110011 %
b100 "
b100 $
b100 #
#25
b1011011 !
b1011011 %
b101 "
b101 $
b101 #
#30
b1011111 !
b1011111 %
b110 "
b110 $
b110 #
#35
b1110000 !
b1110000 %
b111 "
b111 $
b111 #
#40
b1111111 !
b1111111 %
b1000 "
b1000 $
b1000 #
#45
b1111011 !
b1111011 %
b1001 "
b1001 $
b1001 #
#50
b1010 #
