day_03/magnitude_comparator/two_bit_mc/two_bit_mc.v
module two_bit_mc(
	input [1:0]A,
	input [1:0]B,
	output reg greater_than,
	output reg equal,
	output reg lesser_than);
	always@(*)begin
	greater_than=0;
	equal=0;
	lesser_than=0;                                                                                                                                                                                
            if (A>B)
	       greater_than = 1;
	    else if (A==B)
	       equal = 1;                                                                      
	    else if (A<B)                                                                                                                                                                           
	       lesser_than = 1;
        end                                                                                                                                                                                            
        endmodule

day_03/magnitude_comparator/two_bit_mc/two_bit_mc_tb.v
module two_bit_mc_tb();
   reg [1:0]A;
   reg [1:0]B;
   wire greater_than;
   wire equal;
   wire lesser_than;
   integer i,j;
   two_bit_mc inst(A,B,greater_than,equal,lesser_than);
    initial begin
    $monitor("time=%0t|A=%b|B=%b|greater_than=%b|equal=%b|lesser_than=%b",$time,A,B,greater_than,equal,lesser_than);
    $dumpfile("two_bit_mc.vcd");
    $dumpvars;
    for(i=0;i<4;i++)begin
       for(j=0;j<4;j++)begin
        A=i;
	B=j;
       #5;
      end
     end
   $finish;
  end
endmodule

day_03/magnitude_comparator/two_bit_mc/two_bit_mc.vcd
$date
	Mon Oct 13 09:35:15 2025
$end
$version
	Icarus Verilog
$end
$timescale
	1s
$end
$scope module two_bit_mc_tb $end
$var wire 1 ! lesser_than $end
$var wire 1 " greater_than $end
$var wire 1 # equal $end
$var reg 2 $ A [1:0] $end
$var reg 2 % B [1:0] $end
$var integer 32 & i [31:0] $end
$var integer 32 ' j [31:0] $end
$scope module inst $end
$var wire 2 ( A [1:0] $end
$var wire 2 ) B [1:0] $end
$var reg 1 # equal $end
$var reg 1 " greater_than $end
$var reg 1 ! lesser_than $end
$upscope $end
$upscope $end
$enddefinitions $end
$comment Show the parameter values. $end
$dumpall
$end
#0
$dumpvars
b0 )
b0 (
b0 '
b0 &
b0 %
b0 $
1#
0"
0!
$end
#5
1!
0#
b1 %
b1 )
b1 '
#10
1!
b10 %
b10 )
b10 '
#15
1!
b11 %
b11 )
b11 '
#20
1"
0!
b0 %
b0 )
b1 $
b1 (
b1 &
b0 '
#25
1#
0"
b1 %
b1 )
b1 '
#30
1!
0#
b10 %
b10 )
b10 '
#35
1!
b11 %
b11 )
b11 '
#40
1"
0!
b0 %
b0 )
b10 $
b10 (
b10 &
b0 '
#45
1"
b1 %
b1 )
b1 '
#50
1#
0"
b10 %
b10 )
b10 '
#55
1!
0#
b11 %
b11 )
b11 '
#60
1"
0!
b0 %
b0 )
b11 $
b11 (
b11 &
b0 '
#65
1"
b1 %
b1 )
b1 '
#70
1"
b10 %
b10 )
b10 '
#75
1#
0"
b11 %
b11 )
b11 '
#80
b100 &
b100 '
