day_02/full_subtractor/full_subtractor.v
module full_subtractor(input a,b,bin, output d,bout);
 assign d = a^b^bin;
 assign bout = (~a&b) | ((~(a^b))&bin);
endmodule

day_02/full_subtractor/full_subtractor_tb.v
module full_subtractor_tb();

  integer i;
  reg a,b,bin;
  wire d,bout;

  full_subtractor inst(.a(a),.b(b),.bin(bin),.d(d),.bout(bout));

  initial begin
    $dumpfile("full_subtractor.vcd");
    $dumpvars;
  end
  
  initial begin
    $display("time\ta\tb\tbin\t|\td\tbout");

    for(i=0; i<8; i=i+1)begin
       {a,b,bin} = i;
       #5;
       $display("%0t\t%b\t%b\t%b\t|\t%b\t%b",$time,a,b,bin,d,bout);
  end
  $finish;
  end
endmodule

day_02/full_subtractor/full_subtractor.vcd
$date
	Fri Oct 10 18:25:57 2025
$end
$version
	Icarus Verilog
$end
$timescale
	1s
$end
$scope module full_subtractor_tb $end
$var wire 1 ! d $end
$var wire 1 " bout $end
$var reg 1 # a $end
$var reg 1 $ b $end
$var reg 1 % bin $end
$var integer 32 & i [31:0] $end
$scope module inst $end
$var wire 1 # a $end
$var wire 1 $ b $end
$var wire 1 % bin $end
$var wire 1 " bout $end
$var wire 1 ! d $end
$upscope $end
$upscope $end
$enddefinitions $end
$comment Show the parameter values. $end
$dumpall
$end
#0
$dumpvars
b0 &
0%
0$
0#
0"
0!
$end
#5
1"
1!
1%
b1 &
#10
1!
1$
0%
b10 &
#15
0!
1%
b11 &
#20
0"
1!
1#
0$
0%
b100 &
#25
0!
1%
b101 &
#30
0!
1$
0%
b110 &
#35
1"
1!
1%
b111 &
#40
b1000 &
