day_08/Finite_State_Machine/1010_non_overlapping/1010_non_overlapping.v
`timescale 1ns/1ps

module sequence_1010_non_overlapping(
      input clk,rst,
      input [1:0]x,
      output reg q);

parameter [1:0] A = 2'b00,
                B = 2'b01,
                C = 2'b10,
                D = 2'b11;
reg [1:0] state,next_state;

always@(*)begin
      case(state)
         A:next_state = x ? B:A;
         B:next_state = x ? C:B;
         C:next_state = x ? D:A;
         D:next_state = x ? A:B;
         default:next_state = A;
      endcase
end

always@(posedge clk)begin
    if(rst)
      state <= A;
    else
      state <= next_state;
end


always@(*)begin
    if (state == D && x == 1'b0)
        q = 1'b1;
    else
        q = 1'b0;
end
endmodule

day_08/Finite_State_Machine/1010_non_overlapping/1010_non_overlapping_tb.v
module sequence_1010_non_overlapping_tb();
    reg clk,rst;
    reg [1:0]x;
    wire q;

  sequence_1010_non_overlapping inst(clk,rst,x,q);

    initial clk = 0;
    always #5 clk = ~clk;

    initial begin
      $monitor("%0t|clk=%b|rst=%b|x=%b|q=%b",$time,clk,rst,x,q);
      $dumpfile("1010_non_overlapping.vcd");
      $dumpvars;

      rst = 1; x=1;
      #10 rst = 0; x=0;

      #10 x=1;
      #10 x=1;
      #10 x=0;
      #10 x=1;
      #10 x=1;
      #10 x=0;
      #10 $finish;
    end
endmodule

day_08/Finite_State_Machine/1010_non_overlapping/1010_non_overlapping.vcd
$date
	Sat Nov  8 12:50:25 2025
$end
$version
	Icarus Verilog
$end
$timescale
	1ps
$end
$scope module sequence_1010_non_overlapping_tb $end
$var wire 1 ! q $end
$var reg 1 " clk $end
$var reg 1 # rst $end
$var reg 2 $ x [1:0] $end
$scope module inst $end
$var wire 1 " clk $end
$var wire 1 # rst $end
$var wire 2 % x [1:0] $end
$var parameter 2 & A $end
$var parameter 2 ' B $end
$var parameter 2 ( C $end
$var parameter 2 ) D $end
$var reg 2 * next_state [1:0] $end
$var reg 1 ! q $end
$var reg 2 + state [1:0] $end
$upscope $end
$upscope $end
$enddefinitions $end
$comment Show the parameter values. $end
$dumpall
b11 )
b10 (
b1 '
b0 &
$end
#0
$dumpvars
bx +
b0 *
b1 %
b1 $
1#
0"
0!
$end
#5000
b1 *
b0 +
1"
#10000
b0 *
0"
b0 $
b0 %
0#
#15000
1"
#20000
b1 *
0"
b1 $
b1 %
#25000
b10 *
b1 +
1"
#30000
0"
#35000
b11 *
b10 +
1"
#40000
b0 *
0"
b0 $
b0 %
#45000
b0 +
1"
#50000
b1 *
0"
b1 $
b1 %
#55000
b10 *
b1 +
1"
#60000
0"
#65000
b11 *
b10 +
1"
#70000
b0 *
0"
b0 $
b0 %
#75000
b0 +
1"
