day_03/priority_encoder/p_encoder_8x3/p_encoder_8x3.v
module p_encoder_8x3(
	input [7:0] a,
	input en,
	output reg [2:0] y);
	always@(en,a)begin
	if (en==1)begin
	if (a[7]==1) y=4'b111;
	else if(a[6]==1) y=4'b110;
	else if(a[5]==1) y=4'b101; 
	else if(a[4]==1) y=4'b100; 
	else if(a[3]==1) y=4'b011; 
	else if(a[2]==1) y=4'b010; 
	else if(a[1]==1) y=4'b001; 
	else 
	    y=3'b000;
        end
	else 
	    y=3'bzzz;
          end
endmodule

day_03/priority_encoder/p_encoder_8x3/p_encoder_8x3_tb.v
module p_encoder_8x3_();
	reg [7:0] a;
	reg en;
	wire [2:0] y;
	p_encoder_8x3 inst(a,en,y);
	initial begin
	$monitor("time=%0t| a=%b| en=%b| y=%b",$time,a,en,y);
	$dumpfile("p_encoder.vcd");
	$dumpvars;
        en=1;a=128;#5;
	en=1;a=64;#5;
	en=1;a=32;#5; 
	en=1;a=16;#5; 
	en=1;a=8;#5;
        en=1;a=4;#5; 
        en=1;a=2;#5;
	en=0;a=7;#5;
	end
endmodule

day_03/priority_encoder/p_encoder_8x3/p_encoder.vcd
$date
	Sat Oct 11 19:50:58 2025
$end
$version
	Icarus Verilog
$end
$timescale
	1s
$end
$scope module p_encoder_8x3_ $end
$var wire 3 ! y [2:0] $end
$var reg 8 " a [7:0] $end
$var reg 1 # en $end
$scope module inst $end
$var wire 8 $ a [7:0] $end
$var wire 1 # en $end
$var reg 3 % y [2:0] $end
$upscope $end
$upscope $end
$enddefinitions $end
$comment Show the parameter values. $end
$dumpall
$end
#0
$dumpvars
b111 %
b10000000 $
1#
b10000000 "
b111 !
$end
#5
b110 !
b110 %
b1000000 "
b1000000 $
#10
b101 !
b101 %
b100000 "
b100000 $
#15
b100 !
b100 %
b10000 "
b10000 $
#20
b11 !
b11 %
b1000 "
b1000 $
#25
b10 !
b10 %
b100 "
b100 $
#30
b1 !
b1 %
b10 "
b10 $
#35
bz !
bz %
b111 "
b111 $
0#
