day_04/code_converters/excess_3_to_binary/excess_3_to_binary.v
module excess_3_to_binary(
     input [3:0]x,
     output reg [3:0]b);
 
     always@(*)begin
        b = x - 4'd3;
      end
   endmodule

day_04/code_converters/excess_3_to_binary/excess_3_to_binary_tb.v
module excess_3_to_binary_tb();
       reg [3:0]x;
       wire [3:0]b;
       integer i;
       excess_3_to_binary inst(x,b);
       initial begin
       $monitor("time=%0t|x=%b|b=%b",$time,x,b);
       $dumpfile("excess_3_to_binary.vcd");
       $dumpvars;
       x=4'b0000;
       for(i=0;i<16;i++)begin
        x=i;
        #5;
       end
       end
endmodule

day_04/code_converters/excess_3_to_binary/excess_3_to_binary.vcd
$date
	Mon Oct 13 21:01:51 2025
$end
$version
	Icarus Verilog
$end
$timescale
	1s
$end
$scope module excess_3_to_binary_tb $end
$var wire 4 ! b [3:0] $end
$var reg 4 " x [3:0] $end
$var integer 32 # i [31:0] $end
$scope module inst $end
$var wire 4 $ x [3:0] $end
$var reg 4 % b [3:0] $end
$upscope $end
$upscope $end
$enddefinitions $end
$comment Show the parameter values. $end
$dumpall
$end
#0
$dumpvars
b1101 %
b0 $
b0 #
b0 "
b1101 !
$end
#5
b1110 !
b1110 %
b1 "
b1 $
b1 #
#10
b1111 !
b1111 %
b10 "
b10 $
b10 #
#15
b0 !
b0 %
b11 "
b11 $
b11 #
#20
b1 !
b1 %
b100 "
b100 $
b100 #
#25
b10 !
b10 %
b101 "
b101 $
b101 #
#30
b11 !
b11 %
b110 "
b110 $
b110 #
#35
b100 !
b100 %
b111 "
b111 $
b111 #
#40
b101 !
b101 %
b1000 "
b1000 $
b1000 #
#45
b110 !
b110 %
b1001 "
b1001 $
b1001 #
#50
b111 !
b111 %
b1010 "
b1010 $
b1010 #
#55
b1000 !
b1000 %
b1011 "
b1011 $
b1011 #
#60
b1001 !
b1001 %
b1100 "
b1100 $
b1100 #
#65
b1010 !
b1010 %
b1101 "
b1101 $
b1101 #
#70
b1011 !
b1011 %
b1110 "
b1110 $
b1110 #
#75
b1100 !
b1100 %
b1111 "
b1111 $
b1111 #
#80
b10000 #
