day_04/code_converters/gray_to_binary/gray_to_binary.v
module gray_to_binary(
      input [3:0]g,
      output reg  [3:0]b);
    
     always@(*)begin
      b[3] = g[3];
      b[2] = g[3] ^ g[2];
      b[1] = g[2] ^ g[1];
      b[0] = g[1] ^ g[0];
     end
endmodule

day_04/code_converters/gray_to_binary/gray_to_binary_tb.v
module gray_to_binary_tb();
    reg [3:0]g;
    wire [3:0]b;
    integer i;
    gray_to_binary inst(g,b);
    initial begin
    $monitor("time=%0t|g=%b|b=%b",$time,g,b);
    $dumpfile("gray_to_binary.vcd");
    $dumpvars;
    g=4'b0000;
    for(i=0;i<16;i++)begin
     g=i;
     #5;
    end
   end
endmodule

day_04/code_converters/gray_to_binary/gray_to_binary.vcd
$date
	Mon Oct 13 19:53:11 2025
$end
$version
	Icarus Verilog
$end
$timescale
	1s
$end
$scope module gray_to_binary_tb $end
$var wire 4 ! b [3:0] $end
$var reg 4 " g [3:0] $end
$var integer 32 # i [31:0] $end
$scope module inst $end
$var wire 4 $ g [3:0] $end
$var reg 4 % b [3:0] $end
$upscope $end
$upscope $end
$enddefinitions $end
$comment Show the parameter values. $end
$dumpall
$end
#0
$dumpvars
b0 %
b0 $
b0 #
b0 "
b0 !
$end
#5
b1 !
b1 %
b1 "
b1 $
b1 #
#10
b11 !
b11 %
b10 "
b10 $
b10 #
#15
b10 !
b10 %
b11 "
b11 $
b11 #
#20
b110 !
b110 %
b100 "
b100 $
b100 #
#25
b111 !
b111 %
b101 "
b101 $
b101 #
#30
b101 !
b101 %
b110 "
b110 $
b110 #
#35
b100 !
b100 %
b111 "
b111 $
b111 #
#40
b1100 !
b1100 %
b1000 "
b1000 $
b1000 #
#45
b1101 !
b1101 %
b1001 "
b1001 $
b1001 #
#50
b1111 !
b1111 %
b1010 "
b1010 $
b1010 #
#55
b1110 !
b1110 %
b1011 "
b1011 $
b1011 #
#60
b1010 !
b1010 %
b1100 "
b1100 $
b1100 #
#65
b1011 !
b1011 %
b1101 "
b1101 $
b1101 #
#70
b1001 !
b1001 %
b1110 "
b1110 $
b1110 #
#75
b1000 !
b1000 %
b1111 "
b1111 $
b1111 #
#80
b10000 #
