day_02/encoder/decimal_BCD/decimal_BCD.v
module decimal_BCD (
    input [9:0] a,
    output [3:0] y);
  
    assign y[3] = (a[9] | a[8]);
    assign y[2] = (a[7] | a[6] | a[5] | a[4]);
    assign y[1] = (a[7] | a[5] | a[3] | a[2]);
    assign y[0] = (a[9] | a[7] | a[5] | a[3] | a[1]);
endmodule

day_02/encoder/decimal_BCD/decimal_BCD_tb.v
module decimal_BCD_tb();
	integer i;
	reg [9:0] a;
	wire [3:0] y;

	decimal_BCD inst(.a(a),.y(y));
        initial begin
	$monitor("time=%0t| a=%b |y=%b",$time,a,y);
	$dumpfile("decimal_BCD.vcd");
	$dumpvars;
	end

	initial begin
	a=10'b000000000;#5;
	a=10'b000000001;
	for(i=1; i<10; i++)begin
        a = a << 1;
        #5;
        end
end
endmodule

day_02/encoder/decimal_BCD/decimal_BCD.vcd
$date
	Sat Oct 11 13:20:30 2025
$end
$version
	Icarus Verilog
$end
$timescale
	1s
$end
$scope module decimal_BCD_tb $end
$var wire 4 ! y [3:0] $end
$var reg 10 " a [9:0] $end
$var integer 32 # i [31:0] $end
$scope module inst $end
$var wire 10 $ a [9:0] $end
$var wire 4 % y [3:0] $end
$upscope $end
$upscope $end
$enddefinitions $end
$comment Show the parameter values. $end
$dumpall
$end
#0
$dumpvars
b0 %
b0 $
bx #
b0 "
b0 !
$end
#5
b1 !
b1 %
b1 #
b10 "
b10 $
#10
b10 !
b10 %
b100 "
b100 $
b10 #
#15
b11 !
b11 %
b1000 "
b1000 $
b11 #
#20
b100 !
b100 %
b10000 "
b10000 $
b100 #
#25
b111 !
b111 %
b100000 "
b100000 $
b101 #
#30
b100 !
b100 %
b1000000 "
b1000000 $
b110 #
#35
b111 !
b111 %
b10000000 "
b10000000 $
b111 #
#40
b1000 !
b1000 %
b100000000 "
b100000000 $
b1000 #
#45
b1001 !
b1001 %
b1000000000 "
b1000000000 $
b1001 #
#50
b1010 #
