day_03/magnitude_comparator/four_bit_mc/four_bit_mc.v
module four_bit_mc(
   input [3:0]A,
   input [3:0]B,
   output reg greater_than,
   output reg equal,
   output reg less_than);
   always@(*)begin
     greater_than=0;
     equal=0;
     less_than=0;
   if(A>B)
     greater_than = 1;
   else if (A==B)
     equal = 1;
   else if (A<B)
     less_than = 1;
   end
endmodule

day_03/magnitude_comparator/four_bit_mc/four_bit_mc_tb.v
module four_bit_mc_tb();
   reg [3:0]A;
   reg [3:0]B;
   wire greater_than;
   wire equal;
   wire less_than;
   integer i,j;
   four_bit_mc inst(A,B,greater_than,equal,less_than);
    initial begin
    $monitor("time=%0t|A=%b|B=%b|greater_than=%b|equal=%b|less_than=%b",$time,A,B,greater_than,equal,less_than);
    $dumpfile("four_bit_mc.vcd");
    $dumpvars;
    for(i=0;i<8;i++)begin
       for(j=0;j<8;j++)begin
        A=i;
	B=j;
       #5;
      end
     end
   $finish;
  end
endmodule

day_03/magnitude_comparator/four_bit_mc/four_bit_mc.vcd
$date
	Mon Oct 13 09:54:11 2025
$end
$version
	Icarus Verilog
$end
$timescale
	1s
$end
$scope module four_bit_mc_tb $end
$var wire 1 ! less_than $end
$var wire 1 " greater_than $end
$var wire 1 # equal $end
$var reg 4 $ A [3:0] $end
$var reg 4 % B [3:0] $end
$var integer 32 & i [31:0] $end
$var integer 32 ' j [31:0] $end
$scope module inst $end
$var wire 4 ( A [3:0] $end
$var wire 4 ) B [3:0] $end
$var reg 1 # equal $end
$var reg 1 " greater_than $end
$var reg 1 ! less_than $end
$upscope $end
$upscope $end
$enddefinitions $end
$comment Show the parameter values. $end
$dumpall
$end
#0
$dumpvars
b0 )
b0 (
b0 '
b0 &
b0 %
b0 $
1#
0"
0!
$end
#5
1!
0#
b1 %
b1 )
b1 '
#10
1!
b10 %
b10 )
b10 '
#15
1!
b11 %
b11 )
b11 '
#20
1!
b100 %
b100 )
b100 '
#25
1!
b101 %
b101 )
b101 '
#30
1!
b110 %
b110 )
b110 '
#35
1!
b111 %
b111 )
b111 '
#40
1"
0!
b0 %
b0 )
b1 $
b1 (
b1 &
b0 '
#45
1#
0"
b1 %
b1 )
b1 '
#50
1!
0#
b10 %
b10 )
b10 '
#55
1!
b11 %
b11 )
b11 '
#60
1!
b100 %
b100 )
b100 '
#65
1!
b101 %
b101 )
b101 '
#70
1!
b110 %
b110 )
b110 '
#75
1!
b111 %
b111 )
b111 '
#80
1"
0!
b0 %
b0 )
b10 $
b10 (
b10 &
b0 '
#85
1"
b1 %
b1 )
b1 '
#90
1#
0"
b10 %
b10 )
b10 '
#95
1!
0#
b11 %
b11 )
b11 '
#100
1!
b100 %
b100 )
b100 '
#105
1!
b101 %
b101 )
b101 '
#110
1!
b110 %
b110 )
b110 '
#115
1!
b111 %
b111 )
b111 '
#120
1"
0!
b0 %
b0 )
b11 $
b11 (
b11 &
b0 '
#125
1"
b1 %
b1 )
b1 '
#130
1"
b10 %
b10 )
b10 '
#135
1#
0"
b11 %
b11 )
b11 '
#140
1!
0#
b100 %
b100 )
b100 '
#145
1!
b101 %
b101 )
b101 '
#150
1!
b110 %
b110 )
b110 '
#155
1!
b111 %
b111 )
b111 '
#160
1"
0!
b0 %
b0 )
b100 $
b100 (
b100 &
b0 '
#165
1"
b1 %
b1 )
b1 '
#170
1"
b10 %
b10 )
b10 '
#175
1"
b11 %
b11 )
b11 '
#180
1#
0"
b100 %
b100 )
b100 '
#185
1!
0#
b101 %
b101 )
b101 '
#190
1!
b110 %
b110 )
b110 '
#195
1!
b111 %
b111 )
b111 '
#200
1"
0!
b0 %
b0 )
b101 $
b101 (
b101 &
b0 '
#205
1"
b1 %
b1 )
b1 '
#210
1"
b10 %
b10 )
b10 '
#215
1"
b11 %
b11 )
b11 '
#220
1"
b100 %
b100 )
b100 '
#225
1#
0"
b101 %
b101 )
b101 '
#230
1!
0#
b110 %
b110 )
b110 '
#235
1!
b111 %
b111 )
b111 '
#240
1"
0!
b0 %
b0 )
b110 $
b110 (
b110 &
b0 '
#245
1"
b1 %
b1 )
b1 '
#250
1"
b10 %
b10 )
b10 '
#255
1"
b11 %
b11 )
b11 '
#260
1"
b100 %
b100 )
b100 '
#265
1"
b101 %
b101 )
b101 '
#270
1#
0"
b110 %
b110 )
b110 '
#275
1!
0#
b111 %
b111 )
b111 '
#280
1"
0!
b0 %
b0 )
b111 $
b111 (
b111 &
b0 '
#285
1"
b1 %
b1 )
b1 '
#290
1"
b10 %
b10 )
b10 '
#295
1"
b11 %
b11 )
b11 '
#300
1"
b100 %
b100 )
b100 '
#305
1"
b101 %
b101 )
b101 '
#310
1"
b110 %
b110 )
b110 '
#315
1#
0"
b111 %
b111 )
b111 '
#320
b1000 &
b1000 '
