day_02/encoder/encoder_8x3/encoder_8x3.v
module encoder_8x3 (
  input [7:0] a,
  output[2:0] y);
 
  assign y[2] = (a[7]|a[6]|a[5]|a[4]);
  assign y[1] = (a[7]|a[6]|a[3]|a[2]);
  assign y[0] = (a[7]|a[5]|a[3]|a[1]);
endmodule

day_02/encoder/encoder_8x3/encoder_8x3_tb.v
module encoder_8x3_tb();
         integer i;
	 reg [7:0] a;
  	 wire [2:0] y;
	
	encoder_8x3 inst(.a(a),.y(y));
	initial begin
        $dumpfile("encoder_8x3.vcd");
	$dumpvars;
end
	initial begin
		$monitor("time=%0t| a=%b| y=%b",$time,a,y);
		a=8'b00000001;
		for(i=1; i<8; i++)begin
		a=a<<1;
	        #5;
	       end
	       $finish;
       end
       endmodule

day_02/encoder/encoder_8x3/encoder_8x3.vcd
$date
	Sat Oct 11 11:47:42 2025
$end
$version
	Icarus Verilog
$end
$timescale
	1s
$end
$scope module encoder_8x3_tb $end
$var wire 3 ! y [2:0] $end
$var reg 8 " a [7:0] $end
$var integer 32 # i [31:0] $end
$scope module inst $end
$var wire 8 $ a [7:0] $end
$var wire 3 % y [2:0] $end
$upscope $end
$upscope $end
$enddefinitions $end
$comment Show the parameter values. $end
$dumpall
$end
#0
$dumpvars
b1 %
b10 $
b1 #
b10 "
b1 !
$end
#5
b10 !
b10 %
b100 "
b100 $
b10 #
#10
b11 !
b11 %
b1000 "
b1000 $
b11 #
#15
b100 !
b100 %
b10000 "
b10000 $
b100 #
#20
b101 !
b101 %
b100000 "
b100000 $
b101 #
#25
b110 !
b110 %
b1000000 "
b1000000 $
b110 #
#30
b111 !
b111 %
b10000000 "
b10000000 $
b111 #
#35
b1000 #
