day_04/code_converters/binary_to_gray/binary_to_gray.v
module binary_to_gray(
        input [3:0]b,       //b mentioned as binary
	output reg [3:0]g); //g mentioned as gray
 
     always@(*)begin
       g[3] = b[3];
       g[2] = b[3] ^ b[2];
       g[1] = b[2] ^ b[1];
       g[0] = b[1] ^ b[0];
     end
endmodule

day_04/code_converters/binary_to_gray/binary_to_gray_tb.v
module binary_to_gray_tb();
      reg [3:0]b;
      wire [3:0]g;
      integer i;
     binary_to_gray inst(b,g);
      initial begin
        $monitor("time-%0t|b=%b|g=%b",$time,b,g);
	$dumpfile("binary_to_gray.vcd");
	$dumpvars;
	b=4'b0000;
        for(i=0;i<16;i++)begin
           b=i;
	   #5;
          end
        end
endmodule

day_04/code_converters/binary_to_gray/binary_to_gray.vcd
$date
	Mon Oct 13 18:53:53 2025
$end
$version
	Icarus Verilog
$end
$timescale
	1s
$end
$scope module binary_to_gray_tb $end
$var wire 4 ! g [3:0] $end
$var reg 4 " b [3:0] $end
$var integer 32 # i [31:0] $end
$scope module inst $end
$var wire 4 $ b [3:0] $end
$var reg 4 % g [3:0] $end
$upscope $end
$upscope $end
$enddefinitions $end
$comment Show the parameter values. $end
$dumpall
$end
#0
$dumpvars
b0 %
b0 $
b0 #
b0 "
b0 !
$end
#5
b1 !
b1 %
b1 "
b1 $
b1 #
#10
b11 !
b11 %
b10 "
b10 $
b10 #
#15
b10 !
b10 %
b11 "
b11 $
b11 #
#20
b110 !
b110 %
b100 "
b100 $
b100 #
#25
b111 !
b111 %
b101 "
b101 $
b101 #
#30
b101 !
b101 %
b110 "
b110 $
b110 #
#35
b100 !
b100 %
b111 "
b111 $
b111 #
#40
b1100 !
b1100 %
b1000 "
b1000 $
b1000 #
#45
b1101 !
b1101 %
b1001 "
b1001 $
b1001 #
#50
b1111 !
b1111 %
b1010 "
b1010 $
b1010 #
#55
b1110 !
b1110 %
b1011 "
b1011 $
b1011 #
#60
b1010 !
b1010 %
b1100 "
b1100 $
b1100 #
#65
b1011 !
b1011 %
b1101 "
b1101 $
b1101 #
#70
b1001 !
b1001 %
b1110 "
b1110 $
b1110 #
#75
b1000 !
b1000 %
b1111 "
b1111 $
b1111 #
#80
b10000 #
